Workbook

Sheet Yield Curve_USD_workflow
B1: Special Formula
B2: Output Result
B5: Loop Section：
B6: Interest (t) = Yield (t-1)* AS projection (t-1) -> AS projection (t) = AS projection (t-1) + interest (t) -> Existing Bond Mix (t) -> New Bond Mix (t) -> Yield (t) -> Interest (t+1) = Yield (t)* AS projection (t)
D8: Check: | E8: =SUM(C13:EL13,B17,H74:J79) -> 0
B9: Output Result: Overall Asset Yield Curve
B10: i | C10: 0 | D10: 1 | E10: 2 | F10: 3 | G10: 4 | H10: 5 | I10: 6 | J10: 7 | K10: 8 | L10: 9 | M10: 10 | N10: 11 | O10: 12 | P10: 13 | Q10: 14 | R10: 15 | S10: 16 | T10: 17 | U10: 18 | V10: 19 | W10: 20 | X10: 21 | Y10: 22 | Z10: 23 | AA10: 24 | AB10: 25 | AC10: 26 | AD10: 27 | AE10: 28 | AF10: 29 | AG10: 30 | AH10: 31 | AI10: 32 | AJ10: 33 | AK10: 34 | AL10: 35 | AM10: 36 | AN10: 37 | AO10: 38 | AP10: 39 | AQ10: 40 | AR10: 41 | AS10: 42 | AT10: 43 | AU10: 44 | AV10: 45 | AW10: 46 | AX10: 47 | AY10: 48 | AZ10: 49 | BA10: 50 | BB10: 51 | BC10: 52 | BD10: 53 | BE10: 54 | BF10: 55 | BG10: 56 | BH10: 57 | BI10: 58 | BJ10: 59 | BK10: 60 | BL10: 61 | BM10: 62 | BN10: 63 | BO10: 64 | BP10: 65 | BQ10: 66 | BR10: 67 | BS10: 68 | BT10: 69 | BU10: 70 | BV10: 71 | BW10: 72 | BX10: 73 | BY10: 74 | BZ10: 75 | CA10: 76 | CB10: 77 | CC10: 78 | CD10: 79 | CE10: 80 | CF10: 81 | CG10: 82 | CH10: 83 | CI10: 84 | CJ10: 85 | CK10: 86 | CL10: 87 | CM10: 88 | CN10: 89 | CO10: 90 | CP10: 91 | CQ10: 92 | CR10: 93 | CS10: 94 | CT10: 95 | CU10: 96 | CV10: 97 | CW10: 98 | CX10: 99 | CY10: 100 | CZ10: 101 | DA10: 102 | DB10: 103 | DC10: 104 | DD10: 105 | DE10: 106 | DF10: 107 | DG10: 108 | DH10: 109 | DI10: 110 | DJ10: 111 | DK10: 112 | DL10: 113 | DM10: 114 | DN10: 115 | DO10: 116 | DP10: 117 | DQ10: 118 | DR10: 119 | DS10: 120 | DT10: 121 | DU10: 122 | DV10: 123 | DW10: 124 | DX10: 125 | DY10: 126 | DZ10: 127 | EA10: 128 | EB10: 129 | EC10: 130 | ED10: 131 | EE10: 132 | EF10: 133 | EG10: 134 | EH10: 135 | EI10: 136 | EJ10: 137 | EK10: 138 | EL10: 139
B11: Year | C11: =D11-1 -> 45656 | D11: =OtherAssump!$C$5 -> 45657 | E11: =D11+1 -> 45658 | F11: =E11+1 -> 45659 | G11: =F11+1 -> 45660 | H11: =G11+1 -> 45661 | I11: =H11+1 -> 45662 | J11: =I11+1 -> 45663 | K11: =J11+1 -> 45664 | L11: =K11+1 -> 45665 | ... EL11: =EK11+1 -> 45795
B12: Overall Asset Yield Curve | C12: =C51 -> 0.067524375 | D12: =D51 -> 0.069095198 | E12: =E51 -> 0.071037502 | F12: =F51 -> 0.072476579 | G12: =G51 -> 0.074243368 | H12: =H51 -> 0.074022755 | I12: =I51 -> 0.074260785 | J12: =J51 -> 0.074205214 | ... EL12: =EL51 -> 0.075524174
B13: Control | C13: =C12-'[1]3.2.2 Yield Curve_USD'!K35 -> 0 | D13: =D12-'[1]3.2.2 Yield Curve_USD'!L35 -> 0 | E13: =E12-'[1]3.2.2 Yield Curve_USD'!M35 -> 0 | F13: =F12-'[1]3.2.2 Yield Curve_USD'!N35 -> 0 | G13: =G12-'[1]3.2.2 Yield Curve_USD'!O35 -> 0 | H13: =H12-'[1]3.2.2 Yield Curve_USD'!P35 -> 0 | I13: =I12-'[1]3.2.2 Yield Curve_USD'!Q35 -> 0 | J13: =J12-'[1]3.2.2 Yield Curve_USD'!R35 -> 0 | ... EL13: =EL12-'[1]3.2.2 Yield Curve_USD'!ET35 -> 0
B15: Output Result: Flat_IRR
B16: =F83 -> 0.073867569
A17: Control | B17: =B16-'[1]3.2.2 Yield Curve_USD'!$E$10 -> 0
B19: Overall Asset Yield Curve Working
B21: Bond Mix by Year
B22: i | C22: 0 | D22: 1 | E22: 2 | F22: 3 | G22: 4 | H22: 5 | I22: 6 | J22: 7 | K22: 8 | L22: 9 | M22: 10 | N22: 11 | O22: 12 | P22: 13 | Q22: 14 | R22: 15 | S22: 16 | T22: 17 | U22: 18 | V22: 19 | W22: 20 | X22: 21 | Y22: 22 | Z22: 23 | AA22: 24 | AB22: 25 | AC22: 26 | AD22: 27 | AE22: 28 | AF22: 29 | AG22: 30 | AH22: 31 | AI22: 32 | AJ22: 33 | AK22: 34 | AL22: 35 | AM22: 36 | AN22: 37 | AO22: 38 | AP22: 39 | AQ22: 40 | AR22: 41 | AS22: 42 | AT22: 43 | AU22: 44 | AV22: 45 | AW22: 46 | AX22: 47 | AY22: 48 | AZ22: 49 | BA22: 50 | BB22: 51 | BC22: 52 | BD22: 53 | BE22: 54 | BF22: 55 | BG22: 56 | BH22: 57 | BI22: 58 | BJ22: 59 | BK22: 60 | BL22: 61 | BM22: 62 | BN22: 63 | BO22: 64 | BP22: 65 | BQ22: 66 | BR22: 67 | BS22: 68 | BT22: 69 | BU22: 70 | BV22: 71 | BW22: 72 | BX22: 73 | BY22: 74 | BZ22: 75 | CA22: 76 | CB22: 77 | CC22: 78 | CD22: 79 | CE22: 80 | CF22: 81 | CG22: 82 | CH22: 83 | CI22: 84 | CJ22: 85 | CK22: 86 | CL22: 87 | CM22: 88 | CN22: 89 | CO22: 90 | CP22: 91 | CQ22: 92 | CR22: 93 | CS22: 94 | CT22: 95 | CU22: 96 | CV22: 97 | CW22: 98 | CX22: 99 | CY22: 100 | CZ22: 101 | DA22: 102 | DB22: 103 | DC22: 104 | DD22: 105 | DE22: 106 | DF22: 107 | DG22: 108 | DH22: 109 | DI22: 110 | DJ22: 111 | DK22: 112 | DL22: 113 | DM22: 114 | DN22: 115 | DO22: 116 | DP22: 117 | DQ22: 118 | DR22: 119 | DS22: 120 | DT22: 121 | DU22: 122 | DV22: 123 | DW22: 124 | DX22: 125 | DY22: 126 | DZ22: 127 | EA22: 128 | EB22: 129 | EC22: 130 | ED22: 131 | EE22: 132 | EF22: 133 | EG22: 134 | EH22: 135 | EI22: 136 | EJ22: 137 | EK22: 138 | EL22: 139
B23: Exisitng Bond | C23: =C28 -> 0.5109 | D23: =MIN(D28,ExisitngBond!D$14/D118) -> 0.33546234 | E23: =MIN(E28,ExisitngBond!E$14/E118) -> 0.23994274 | F23: =MIN(F28,ExisitngBond!F$14/F118) -> 0.17920894 | G23: =MIN(G28,ExisitngBond!G$14/G118) -> 0.13903723 | H23: =MIN(H28,ExisitngBond!H$14/H118) -> 0.11442346 | I23: =MIN(I28,ExisitngBond!I$14/I118) -> 0.10115216 | J23: =MIN(J28,ExisitngBond!J$14/J118) -> 0.093810499 | K23: =MIN(K28,ExisitngBond!K$14/K118) -> 0.0903688 | ... EL23: =MIN(EL28,ExisitngBond!EL$14/EL118) -> 0
B24: New Bond | C24: =C28-C23 -> 0 | D24: =D28-D23 -> 0.14634903 | E24: =E28-E23 -> 0.21278002 | F24: =F28-F23 -> 0.24442518 | G24: =G28-G23 -> 0.25550827 | H24: =H28-H23 -> 0.28012205 | I24: =I28-I23 -> 0.29339334 | J24: =J28-J23 -> 0.30073501 | ... EL24: =EL28-EL23 -> 0.3945455
B26: Asset Mix by Year
B27: i | C27: 0 | D27: 1 | E27: 2 | F27: 3 | G27: 4 | H27: 5 | I27: 6 | J27: 7 | K27: 8 | L27: 9 | M27: 10 | N27: 11 | O27: 12 | P27: 13 | Q27: 14 | R27: 15 | S27: 16 | T27: 17 | U27: 18 | V27: 19 | W27: 20 | X27: 21 | Y27: 22 | Z27: 23 | AA27: 24 | AB27: 25 | AC27: 26 | AD27: 27 | AE27: 28 | AF27: 29 | AG27: 30 | AH27: 31 | AI27: 32 | AJ27: 33 | AK27: 34 | AL27: 35 | AM27: 36 | AN27: 37 | AO27: 38 | AP27: 39 | AQ27: 40 | AR27: 41 | AS27: 42 | AT27: 43 | AU27: 44 | AV27: 45 | AW27: 46 | AX27: 47 | AY27: 48 | AZ27: 49 | BA27: 50 | BB27: 51 | BC27: 52 | BD27: 53 | BE27: 54 | BF27: 55 | BG27: 56 | BH27: 57 | BI27: 58 | BJ27: 59 | BK27: 60 | BL27: 61 | BM27: 62 | BN27: 63 | BO27: 64 | BP27: 65 | BQ27: 66 | BR27: 67 | BS27: 68 | BT27: 69 | BU27: 70 | BV27: 71 | BW27: 72 | BX27: 73 | BY27: 74 | BZ27: 75 | CA27: 76 | CB27: 77 | CC27: 78 | CD27: 79 | CE27: 80 | CF27: 81 | CG27: 82 | CH27: 83 | CI27: 84 | CJ27: 85 | CK27: 86 | CL27: 87 | CM27: 88 | CN27: 89 | CO27: 90 | CP27: 91 | CQ27: 92 | CR27: 93 | CS27: 94 | CT27: 95 | CU27: 96 | CV27: 97 | CW27: 98 | CX27: 99 | CY27: 100 | CZ27: 101 | DA27: 102 | DB27: 103 | DC27: 104 | DD27: 105 | DE27: 106 | DF27: 107 | DG27: 108 | DH27: 109 | DI27: 110 | DJ27: 111 | DK27: 112 | DL27: 113 | DM27: 114 | DN27: 115 | DO27: 116 | DP27: 117 | DQ27: 118 | DR27: 119 | DS27: 120 | DT27: 121 | DU27: 122 | DV27: 123 | DW27: 124 | DX27: 125 | DY27: 126 | DZ27: 127 | EA27: 128 | EB27: 129 | EC27: 130 | ED27: 131 | EE27: 132 | EF27: 133 | EG27: 134 | EH27: 135 | EI27: 136 | EJ27: 137 | EK27: 138 | EL27: 139
B28: Bond | C28: =InititalAssetMix!$C$5 -> 0.5109 | D28: =$C28+($G28-$C28)*D$27/$G$27 -> 0.48181138 | E28: =$C28+($G28-$C28)*E$27/$G$27 -> 0.45272275 | F28: =$C28+($G28-$C28)*F$27/$G$27 -> 0.42363413 | G28: =SUMPRODUCT(AssetAssump!$D$6:$D$28,N(AssetAssump!$B$6:$B$28=$B28)) -> 0.3945455 | H28: =SUMPRODUCT(AssetAssump!$D$6:$D$28,N(AssetAssump!$B$6:$B$28=$B28)) -> 0.3945455 | I28: =SUMPRODUCT(AssetAssump!$D$6:$D$28,N(AssetAssump!$B$6:$B$28=$B28)) -> 0.3945455 | J28: =SUMPRODUCT(AssetAssump!$D$6:$D$28,N(AssetAssump!$B$6:$B$28=$B28)) -> 0.3945455 | K28: =SUMPRODUCT(AssetAssump!$D$6:$D$28,N(AssetAssump!$B$6:$B$28=$B28)) -> 0.3945455 | L28: =SUMPRODUCT(AssetAssump!$D$6:$D$28,N(AssetAssump!$B$6:$B$28=$B28)) -> 0.3945455 | M28: =SUMPRODUCT(AssetAssump!$D$6:$D$28,N(AssetAssump!$B$6:$B$28=$B28)) -> 0.3945455 | N28: =SUMPRODUCT(AssetAssump!$D$6:$D$28,N(AssetAssump!$B$6:$B$28=$B28)) -> 0.3945455 | ... EL28: =SUMPRODUCT(AssetAssump!$D$6:$D$28,N(AssetAssump!$B$6:$B$28=$B28)) -> 0.3945455
B29: Equity | C29: =InititalAssetMix!$C$6 -> 0.4151 | D29: =$C29+($G29-$C29)*D$27/$G$27 -> 0.396958 | E29: =$C29+($G29-$C29)*E$27/$G$27 -> 0.37881599 | F29: =$C29+($G29-$C29)*F$27/$G$27 -> 0.36067399 | G29: =SUMPRODUCT(AssetAssump!$D$6:$D$28,N(AssetAssump!$B$6:$B$28=$B29)) -> 0.34253198 | H29: =SUMPRODUCT(AssetAssump!$D$6:$D$28,N(AssetAssump!$B$6:$B$28=$B29)) -> 0.34253198 | I29: =SUMPRODUCT(AssetAssump!$D$6:$D$28,N(AssetAssump!$B$6:$B$28=$B29)) -> 0.34253198 | J29: =SUMPRODUCT(AssetAssump!$D$6:$D$28,N(AssetAssump!$B$6:$B$28=$B29)) -> 0.34253198 | K29: =SUMPRODUCT(AssetAssump!$D$6:$D$28,N(AssetAssump!$B$6:$B$28=$B29)) -> 0.34253198 | L29: =SUMPRODUCT(AssetAssump!$D$6:$D$28,N(AssetAssump!$B$6:$B$28=$B29)) -> 0.34253198 | M29: =SUMPRODUCT(AssetAssump!$D$6:$D$28,N(AssetAssump!$B$6:$B$28=$B29)) -> 0.34253198 | N29: =SUMPRODUCT(AssetAssump!$D$6:$D$28,N(AssetAssump!$B$6:$B$28=$B29)) -> 0.34253198 | ... EL29: =SUMPRODUCT(AssetAssump!$D$6:$D$28,N(AssetAssump!$B$6:$B$28=$B29)) -> 0.34253198
B30: Alternatives | C30: =InititalAssetMix!$C$7 -> 0.0523 | D30: =$C30+($G30-$C30)*D$27/$G$27 -> 0.101725 | E30: =$C30+($G30-$C30)*E$27/$G$27 -> 0.15115 | F30: =$C30+($G30-$C30)*F$27/$G$27 -> 0.200575 | G30: =SUMPRODUCT(AssetAssump!$D$6:$D$28,N(AssetAssump!$B$6:$B$28=$B30)) -> 0.25 | H30: =SUMPRODUCT(AssetAssump!$D$6:$D$28,N(AssetAssump!$B$6:$B$28=$B30)) -> 0.25 | I30: =SUMPRODUCT(AssetAssump!$D$6:$D$28,N(AssetAssump!$B$6:$B$28=$B30)) -> 0.25 | J30: =SUMPRODUCT(AssetAssump!$D$6:$D$28,N(AssetAssump!$B$6:$B$28=$B30)) -> 0.25 | K30: =SUMPRODUCT(AssetAssump!$D$6:$D$28,N(AssetAssump!$B$6:$B$28=$B30)) -> 0.25 | L30: =SUMPRODUCT(AssetAssump!$D$6:$D$28,N(AssetAssump!$B$6:$B$28=$B30)) -> 0.25 | M30: =SUMPRODUCT(AssetAssump!$D$6:$D$28,N(AssetAssump!$B$6:$B$28=$B30)) -> 0.25 | N30: =SUMPRODUCT(AssetAssump!$D$6:$D$28,N(AssetAssump!$B$6:$B$28=$B30)) -> 0.25 | ... EL30: =SUMPRODUCT(AssetAssump!$D$6:$D$28,N(AssetAssump!$B$6:$B$28=$B30)) -> 0.25
B31: Others | C31: =InititalAssetMix!$C$8 -> 0.0010358475 | D31: =$C31+($G31-$C31)*D$27/$G$27 -> 0.00077688563 | E31: =$C31+($G31-$C31)*E$27/$G$27 -> 0.00051792375 | F31: =$C31+($G31-$C31)*F$27/$G$27 -> 0.00025896188 | G31: =SUMPRODUCT(AssetAssump!$D$6:$D$28,N(AssetAssump!$B$6:$B$28=$B31)) -> 0 | H31: =SUMPRODUCT(AssetAssump!$D$6:$D$28,N(AssetAssump!$B$6:$B$28=$B31)) -> 0 | I31: =SUMPRODUCT(AssetAssump!$D$6:$D$28,N(AssetAssump!$B$6:$B$28=$B31)) -> 0 | J31: =SUMPRODUCT(AssetAssump!$D$6:$D$28,N(AssetAssump!$B$6:$B$28=$B31)) -> 0 | K31: =SUMPRODUCT(AssetAssump!$D$6:$D$28,N(AssetAssump!$B$6:$B$28=$B31)) -> 0 | L31: =SUMPRODUCT(AssetAssump!$D$6:$D$28,N(AssetAssump!$B$6:$B$28=$B31)) -> 0 | M31: =SUMPRODUCT(AssetAssump!$D$6:$D$28,N(AssetAssump!$B$6:$B$28=$B31)) -> 0 | N31: =SUMPRODUCT(AssetAssump!$D$6:$D$28,N(AssetAssump!$B$6:$B$28=$B31)) -> 0 | ... EL31: =SUMPRODUCT(AssetAssump!$D$6:$D$28,N(AssetAssump!$B$6:$B$28=$B31)) -> 0
B33: Variables
B34: Total bond mix | C34: =SUM(AssetAssump!$D$7:$D$9) -> 0.3945455
B35: Risk free rate | C35: =AssetAssump!$E$24 -> 0.033
B36: Reinvestment Bond Yield Yr1-30 | C36: =SUMPRODUCT(AssetAssump!$D$7:$D$9,AssetAssump!$E$7:$E$9)/'Yield Curve_USD_workflow'!C34 -> 0.048405894
B37: Reinvestment Bond Yield Yr40+ | C37: =OtherAssump!$C$6+'Yield Curve_USD_workflow'!C36-'Yield Curve_USD_workflow'!C35 -> 0.052968249
B38: Asset Interpolation Spread | C38: =(OtherAssump!$C$6-C35)*C34 -> 0.0018000567
B40: i | C40: 0 | D40: 1 | E40: 2 | F40: 3 | G40: 4 | H40: 5 | I40: 6 | J40: 7 | K40: 8 | L40: 9 | M40: 10 | N40: 11 | O40: 12 | P40: 13 | Q40: 14 | R40: 15 | S40: 16 | T40: 17 | U40: 18 | V40: 19 | W40: 20 | X40: 21 | Y40: 22 | Z40: 23 | AA40: 24 | AB40: 25 | AC40: 26 | AD40: 27 | AE40: 28 | AF40: 29 | AG40: 30 | AH40: 31 | AI40: 32 | AJ40: 33 | AK40: 34 | AL40: 35 | AM40: 36 | AN40: 37 | AO40: 38 | AP40: 39 | AQ40: 40 | AR40: 41 | AS40: 42 | AT40: 43 | AU40: 44 | AV40: 45 | AW40: 46 | AX40: 47 | AY40: 48 | AZ40: 49 | BA40: 50 | BB40: 51 | BC40: 52 | BD40: 53 | BE40: 54 | BF40: 55 | BG40: 56 | BH40: 57 | BI40: 58 | BJ40: 59 | BK40: 60 | BL40: 61 | BM40: 62 | BN40: 63 | BO40: 64 | BP40: 65 | BQ40: 66 | BR40: 67 | BS40: 68 | BT40: 69 | BU40: 70 | BV40: 71 | BW40: 72 | BX40: 73 | BY40: 74 | BZ40: 75 | CA40: 76 | CB40: 77 | CC40: 78 | CD40: 79 | CE40: 80 | CF40: 81 | CG40: 82 | CH40: 83 | CI40: 84 | CJ40: 85 | CK40: 86 | CL40: 87 | CM40: 88 | CN40: 89 | CO40: 90 | CP40: 91 | CQ40: 92 | CR40: 93 | CS40: 94 | CT40: 95 | CU40: 96 | CV40: 97 | CW40: 98 | CX40: 99 | CY40: 100 | CZ40: 101 | DA40: 102 | DB40: 103 | DC40: 104 | DD40: 105 | DE40: 106 | DF40: 107 | DG40: 108 | DH40: 109 | DI40: 110 | DJ40: 111 | DK40: 112 | DL40: 113 | DM40: 114 | DN40: 115 | DO40: 116 | DP40: 117 | DQ40: 118 | DR40: 119 | DS40: 120 | DT40: 121 | DU40: 122 | DV40: 123 | DW40: 124 | DX40: 125 | DY40: 126 | DZ40: 127 | EA40: 128 | EB40: 129 | EC40: 130 | ED40: 131 | EE40: 132 | EF40: 133 | EG40: 134 | EH40: 135 | EI40: 136 | EJ40: 137 | EK40: 138 | EL40: 139
B41: Bond Reinvestment Yield Method 1 | C41: =IF((C40-$D$40)<=30, $C$36, IF(AND((C40-$D$40)>30,(C40-$D$40)<=40), $C$36+($C$37-$C$36)*(C40-$D$40-30)/10, $C$37)) -> 0.048405894 | D41: =IF((D40-$D$40)<=30, $C$36, IF(AND((D40-$D$40)>30,(D40-$D$40)<=40), $C$36+($C$37-$C$36)*(D40-$D$40-30)/10, $C$37)) -> 0.048405894 | E41: =IF((E40-$D$40)<=30, $C$36, IF(AND((E40-$D$40)>30,(E40-$D$40)<=40), $C$36+($C$37-$C$36)*(E40-$D$40-30)/10, $C$37)) -> 0.048405894 | F41: =IF((F40-$D$40)<=30, $C$36, IF(AND((F40-$D$40)>30,(F40-$D$40)<=40), $C$36+($C$37-$C$36)*(F40-$D$40-30)/10, $C$37)) -> 0.048405894 | G41: =IF((G40-$D$40)<=30, $C$36, IF(AND((G40-$D$40)>30,(G40-$D$40)<=40), $C$36+($C$37-$C$36)*(G40-$D$40-30)/10, $C$37)) -> 0.048405894 | H41: =IF((H40-$D$40)<=30, $C$36, IF(AND((H40-$D$40)>30,(H40-$D$40)<=40), $C$36+($C$37-$C$36)*(H40-$D$40-30)/10, $C$37)) -> 0.048405894 | I41: =IF((I40-$D$40)<=30, $C$36, IF(AND((I40-$D$40)>30,(I40-$D$40)<=40), $C$36+($C$37-$C$36)*(I40-$D$40-30)/10, $C$37)) -> 0.048405894 | J41: =IF((J40-$D$40)<=30, $C$36, IF(AND((J40-$D$40)>30,(J40-$D$40)<=40), $C$36+($C$37-$C$36)*(J40-$D$40-30)/10, $C$37)) -> 0.048405894 | ... EL41: =IF((EL40-$D$40)<=30, $C$36, IF(AND((EL40-$D$40)>30,(EL40-$D$40)<=40), $C$36+($C$37-$C$36)*(EL40-$D$40-30)/10, $C$37)) -> 0.052968249
B42: Bond Reinvestment Yield Method 2 | C42: =$C$36 -> 0.048405894 | D42: =$C$36 -> 0.048405894 | E42: =$C$36 -> 0.048405894 | F42: =$C$36 -> 0.048405894 | G42: =$C$36 -> 0.048405894 | H42: =$C$36 -> 0.048405894 | I42: =$C$36 -> 0.048405894 | J42: =$C$36 -> 0.048405894 | ... EL42: =$C$36 -> 0.048405894
B44: Yield Curve
B45: i | C45: 0 | D45: 1 | E45: 2 | F45: 3 | G45: 4 | H45: 5 | I45: 6 | J45: 7 | K45: 8 | L45: 9 | M45: 10 | N45: 11 | O45: 12 | P45: 13 | Q45: 14 | R45: 15 | S45: 16 | T45: 17 | U45: 18 | V45: 19 | W45: 20 | X45: 21 | Y45: 22 | Z45: 23 | AA45: 24 | AB45: 25 | AC45: 26 | AD45: 27 | AE45: 28 | AF45: 29 | AG45: 30 | AH45: 31 | AI45: 32 | AJ45: 33 | AK45: 34 | AL45: 35 | AM45: 36 | AN45: 37 | AO45: 38 | AP45: 39 | AQ45: 40 | AR45: 41 | AS45: 42 | AT45: 43 | AU45: 44 | AV45: 45 | AW45: 46 | AX45: 47 | AY45: 48 | AZ45: 49 | BA45: 50 | BB45: 51 | BC45: 52 | BD45: 53 | BE45: 54 | BF45: 55 | BG45: 56 | BH45: 57 | BI45: 58 | BJ45: 59 | BK45: 60 | BL45: 61 | BM45: 62 | BN45: 63 | BO45: 64 | BP45: 65 | BQ45: 66 | BR45: 67 | BS45: 68 | BT45: 69 | BU45: 70 | BV45: 71 | BW45: 72 | BX45: 73 | BY45: 74 | BZ45: 75 | CA45: 76 | CB45: 77 | CC45: 78 | CD45: 79 | CE45: 80 | CF45: 81 | CG45: 82 | CH45: 83 | CI45: 84 | CJ45: 85 | CK45: 86 | CL45: 87 | CM45: 88 | CN45: 89 | CO45: 90 | CP45: 91 | CQ45: 92 | CR45: 93 | CS45: 94 | CT45: 95 | CU45: 96 | CV45: 97 | CW45: 98 | CX45: 99 | CY45: 100 | CZ45: 101 | DA45: 102 | DB45: 103 | DC45: 104 | DD45: 105 | DE45: 106 | DF45: 107 | DG45: 108 | DH45: 109 | DI45: 110 | DJ45: 111 | DK45: 112 | DL45: 113 | DM45: 114 | DN45: 115 | DO45: 116 | DP45: 117 | DQ45: 118 | DR45: 119 | DS45: 120 | DT45: 121 | DU45: 122 | DV45: 123 | DW45: 124 | DX45: 125 | DY45: 126 | DZ45: 127 | EA45: 128 | EB45: 129 | EC45: 130 | ED45: 131 | EE45: 132 | EF45: 133 | EG45: 134 | EH45: 135 | EI45: 136 | EJ45: 137 | EK45: 138 | EL45: 139
B46: Bond Reinvestment Yield | C46: =INDEX(C$41:C$42,MATCH(OtherAssump!$C$11,$B$41:$B$42,0)) -> 0.048405894 | D46: =INDEX(D$41:D$42,MATCH(OtherAssump!$C$11,$B$41:$B$42,0)) -> 0.048405894 | E46: =INDEX(E$41:E$42,MATCH(OtherAssump!$C$11,$B$41:$B$42,0)) -> 0.048405894 | F46: =INDEX(F$41:F$42,MATCH(OtherAssump!$C$11,$B$41:$B$42,0)) -> 0.048405894 | G46: =INDEX(G$41:G$42,MATCH(OtherAssump!$C$11,$B$41:$B$42,0)) -> 0.048405894 | H46: =INDEX(H$41:H$42,MATCH(OtherAssump!$C$11,$B$41:$B$42,0)) -> 0.048405894 | I46: =INDEX(I$41:I$42,MATCH(OtherAssump!$C$11,$B$41:$B$42,0)) -> 0.048405894 | J46: =INDEX(J$41:J$42,MATCH(OtherAssump!$C$11,$B$41:$B$42,0)) -> 0.048405894 | ... EL46: =INDEX(EL$41:EL$42,MATCH(OtherAssump!$C$11,$B$41:$B$42,0)) -> 0.052968249
B47: Bond Yield Curve | C47: =(C23*ExisitngBond!C8+C24*C41)/SUM(C23:C24) -> 0.048043055 | D47: =(D23*ExisitngBond!D8+D24*D41)/SUM(D23:D24) -> 0.048153266 | E47: =(E23*ExisitngBond!E8+E24*E41)/SUM(E23:E24) -> 0.049097841 | F47: =(F23*ExisitngBond!F8+F24*F41)/SUM(F23:F24) -> 0.049019649 | G47: =(G23*ExisitngBond!G8+G24*G41)/SUM(G23:G24) -> 0.049763918 | H47: =(H23*ExisitngBond!H8+H24*H41)/SUM(H23:H24) -> 0.049211986 | I47: =(I23*ExisitngBond!I8+I24*I41)/SUM(I23:I24) -> 0.049807491 | J47: =(J23*ExisitngBond!J8+J24*J41)/SUM(J23:J24) -> 0.049668463 | ... EL47: =(EL23*ExisitngBond!EL8+EL24*EL41)/SUM(EL23:EL24) -> 0.052968249
B48: Equity Yield Curve | C48: =IFERROR(SUMPRODUCT(AssetAssump!$E$6:$E$28, AssetAssump!$D$6:$D$28, N(AssetAssump!$B$6:$B$28="Equity") / SUMIF(AssetAssump!$B$6:$B$28,"Equity",AssetAssump!$D$6:$D$28)),0) -> 0.0884 | D48: =IFERROR(SUMPRODUCT(AssetAssump!$E$6:$E$28, AssetAssump!$D$6:$D$28, N(AssetAssump!$B$6:$B$28="Equity") / SUMIF(AssetAssump!$B$6:$B$28,"Equity",AssetAssump!$D$6:$D$28)),0) -> 0.0884 | E48: =IFERROR(SUMPRODUCT(AssetAssump!$E$6:$E$28, AssetAssump!$D$6:$D$28, N(AssetAssump!$B$6:$B$28="Equity") / SUMIF(AssetAssump!$B$6:$B$28,"Equity",AssetAssump!$D$6:$D$28)),0) -> 0.0884 | F48: =IFERROR(SUMPRODUCT(AssetAssump!$E$6:$E$28, AssetAssump!$D$6:$D$28, N(AssetAssump!$B$6:$B$28="Equity") / SUMIF(AssetAssump!$B$6:$B$28,"Equity",AssetAssump!$D$6:$D$28)),0) -> 0.0884 | G48: =IFERROR(SUMPRODUCT(AssetAssump!$E$6:$E$28, AssetAssump!$D$6:$D$28, N(AssetAssump!$B$6:$B$28="Equity") / SUMIF(AssetAssump!$B$6:$B$28,"Equity",AssetAssump!$D$6:$D$28)),0) -> 0.0884 | H48: =IFERROR(SUMPRODUCT(AssetAssump!$E$6:$E$28, AssetAssump!$D$6:$D$28, N(AssetAssump!$B$6:$B$28="Equity") / SUMIF(AssetAssump!$B$6:$B$28,"Equity",AssetAssump!$D$6:$D$28)),0) -> 0.0884 | I48: =IFERROR(SUMPRODUCT(AssetAssump!$E$6:$E$28, AssetAssump!$D$6:$D$28, N(AssetAssump!$B$6:$B$28="Equity") / SUMIF(AssetAssump!$B$6:$B$28,"Equity",AssetAssump!$D$6:$D$28)),0) -> 0.0884 | J48: =IFERROR(SUMPRODUCT(AssetAssump!$E$6:$E$28, AssetAssump!$D$6:$D$28, N(AssetAssump!$B$6:$B$28="Equity") / SUMIF(AssetAssump!$B$6:$B$28,"Equity",AssetAssump!$D$6:$D$28)),0) -> 0.0884 | ... EL48: =IFERROR(SUMPRODUCT(AssetAssump!$E$6:$E$28, AssetAssump!$D$6:$D$28, N(AssetAssump!$B$6:$B$28="Equity") / SUMIF(AssetAssump!$B$6:$B$28,"Equity",AssetAssump!$D$6:$D$28)),0) -> 0.0884
B49: Alternatives Yield | C49: =IFERROR(SUMPRODUCT(AssetAssump!$E$6:$E$28, AssetAssump!$D$6:$D$28, N(AssetAssump!$B$6:$B$28="Alternatives") / SUMIF(AssetAssump!$B$6:$B$28,"Alternatives",AssetAssump!$D$6:$D$28)),0) -> 0.09348 | D49: =IFERROR(SUMPRODUCT(AssetAssump!$E$6:$E$28, AssetAssump!$D$6:$D$28, N(AssetAssump!$B$6:$B$28="Alternatives") / SUMIF(AssetAssump!$B$6:$B$28,"Alternatives",AssetAssump!$D$6:$D$28)),0) -> 0.09348 | E49: =IFERROR(SUMPRODUCT(AssetAssump!$E$6:$E$28, AssetAssump!$D$6:$D$28, N(AssetAssump!$B$6:$B$28="Alternatives") / SUMIF(AssetAssump!$B$6:$B$28,"Alternatives",AssetAssump!$D$6:$D$28)),0) -> 0.09348 | F49: =IFERROR(SUMPRODUCT(AssetAssump!$E$6:$E$28, AssetAssump!$D$6:$D$28, N(AssetAssump!$B$6:$B$28="Alternatives") / SUMIF(AssetAssump!$B$6:$B$28,"Alternatives",AssetAssump!$D$6:$D$28)),0) -> 0.09348 | G49: =IFERROR(SUMPRODUCT(AssetAssump!$E$6:$E$28, AssetAssump!$D$6:$D$28, N(AssetAssump!$B$6:$B$28="Alternatives") / SUMIF(AssetAssump!$B$6:$B$28,"Alternatives",AssetAssump!$D$6:$D$28)),0) -> 0.09348 | H49: =IFERROR(SUMPRODUCT(AssetAssump!$E$6:$E$28, AssetAssump!$D$6:$D$28, N(AssetAssump!$B$6:$B$28="Alternatives") / SUMIF(AssetAssump!$B$6:$B$28,"Alternatives",AssetAssump!$D$6:$D$28)),0) -> 0.09348 | I49: =IFERROR(SUMPRODUCT(AssetAssump!$E$6:$E$28, AssetAssump!$D$6:$D$28, N(AssetAssump!$B$6:$B$28="Alternatives") / SUMIF(AssetAssump!$B$6:$B$28,"Alternatives",AssetAssump!$D$6:$D$28)),0) -> 0.09348 | J49: =IFERROR(SUMPRODUCT(AssetAssump!$E$6:$E$28, AssetAssump!$D$6:$D$28, N(AssetAssump!$B$6:$B$28="Alternatives") / SUMIF(AssetAssump!$B$6:$B$28,"Alternatives",AssetAssump!$D$6:$D$28)),0) -> 0.09348 | ... EL49: =IFERROR(SUMPRODUCT(AssetAssump!$E$6:$E$28, AssetAssump!$D$6:$D$28, N(AssetAssump!$B$6:$B$28="Alternatives") / SUMIF(AssetAssump!$B$6:$B$28,"Alternatives",AssetAssump!$D$6:$D$28)),0) -> 0.09348
B50: Others Yield | C50: =IFERROR(SUMPRODUCT(AssetAssump!$E$6:$E$28, AssetAssump!$D$6:$D$28, N(AssetAssump!$B$6:$B$28="Others") / SUMIF(AssetAssump!$B$6:$B$28,"Others",AssetAssump!$D$6:$D$28)),0) -> 0 | D50: =IFERROR(SUMPRODUCT(AssetAssump!$E$6:$E$28, AssetAssump!$D$6:$D$28, N(AssetAssump!$B$6:$B$28="Others") / SUMIF(AssetAssump!$B$6:$B$28,"Others",AssetAssump!$D$6:$D$28)),0) -> 0 | E50: =IFERROR(SUMPRODUCT(AssetAssump!$E$6:$E$28, AssetAssump!$D$6:$D$28, N(AssetAssump!$B$6:$B$28="Others") / SUMIF(AssetAssump!$B$6:$B$28,"Others",AssetAssump!$D$6:$D$28)),0) -> 0 | F50: =IFERROR(SUMPRODUCT(AssetAssump!$E$6:$E$28, AssetAssump!$D$6:$D$28, N(AssetAssump!$B$6:$B$28="Others") / SUMIF(AssetAssump!$B$6:$B$28,"Others",AssetAssump!$D$6:$D$28)),0) -> 0 | G50: =IFERROR(SUMPRODUCT(AssetAssump!$E$6:$E$28, AssetAssump!$D$6:$D$28, N(AssetAssump!$B$6:$B$28="Others") / SUMIF(AssetAssump!$B$6:$B$28,"Others",AssetAssump!$D$6:$D$28)),0) -> 0 | H50: =IFERROR(SUMPRODUCT(AssetAssump!$E$6:$E$28, AssetAssump!$D$6:$D$28, N(AssetAssump!$B$6:$B$28="Others") / SUMIF(AssetAssump!$B$6:$B$28,"Others",AssetAssump!$D$6:$D$28)),0) -> 0 | I50: =IFERROR(SUMPRODUCT(AssetAssump!$E$6:$E$28, AssetAssump!$D$6:$D$28, N(AssetAssump!$B$6:$B$28="Others") / SUMIF(AssetAssump!$B$6:$B$28,"Others",AssetAssump!$D$6:$D$28)),0) -> 0 | J50: =IFERROR(SUMPRODUCT(AssetAssump!$E$6:$E$28, AssetAssump!$D$6:$D$28, N(AssetAssump!$B$6:$B$28="Others") / SUMIF(AssetAssump!$B$6:$B$28,"Others",AssetAssump!$D$6:$D$28)),0) -> 0 | ... EL50: =IFERROR(SUMPRODUCT(AssetAssump!$E$6:$E$28, AssetAssump!$D$6:$D$28, N(AssetAssump!$B$6:$B$28="Others") / SUMIF(AssetAssump!$B$6:$B$28,"Others",AssetAssump!$D$6:$D$28)),0) -> 0
B51: Overall Asset Yield Curve | C51: =(C28*C47+C29*C48+C30*C49+C31*C50)/(C28+SUM(C29:C31))-OtherAssump!$C$10 -> 0.067524375 | D51: =(D28*D47+D29*D48+D30*D49+D31*D50)/(D28+SUM(D29:D31))-OtherAssump!$C$10 -> 0.069095198 | E51: =(E28*E47+E29*E48+E30*E49+E31*E50)/(E28+SUM(E29:E31))-OtherAssump!$C$10 -> 0.071037502 | F51: =(F28*F47+F29*F48+F30*F49+F31*F50)/(F28+SUM(F29:F31))-OtherAssump!$C$10 -> 0.072476579 | G51: =(G28*G47+G29*G48+G30*G49+G31*G50)/(G28+SUM(G29:G31))-OtherAssump!$C$10 -> 0.074243368 | H51: =(H28*H47+H29*H48+H30*H49+H31*H50)/(H28+SUM(H29:H31))-OtherAssump!$C$10 -> 0.074022755 | I51: =(I28*I47+I29*I48+I30*I49+I31*I50)/(I28+SUM(I29:I31))-OtherAssump!$C$10 -> 0.074260785 | J51: =(J28*J47+J29*J48+J30*J49+J31*J50)/(J28+SUM(J29:J31))-OtherAssump!$C$10 -> 0.074205214 | ... EL51: =(EL28*EL47+EL29*EL48+EL30*EL49+EL31*EL50)/(EL28+SUM(EL29:EL31))-OtherAssump!$C$10 -> 0.075524174
B52: Discounted Factor *Yield Curve | C52: =1 -> 1 | D52: =C52*(1+C51)^(-0.5)*(1+D51)^(-0.5) -> 0.93605833 | E52: =D52*(1+D51)^(-0.5)*(1+E51)^(-0.5) -> 0.87476698 | F52: =E52*(1+E51)^(-0.5)*(1+F51)^(-0.5) -> 0.81619914 | G52: =F52*(1+F51)^(-0.5)*(1+G51)^(-0.5) -> 0.76041537 | H52: =G52*(1+G51)^(-0.5)*(1+H51)^(-0.5) -> 0.70793405 | I52: =H52*(1+H51)^(-0.5)*(1+I51)^(-0.5) -> 0.65906948 | J52: =I52*(1+I51)^(-0.5)*(1+J51)^(-0.5) -> 0.61352563 | K52: =J52*(1+J51)^(-0.5)*(1+K51)^(-0.5) -> 0.57117984 | ... EL52: =EK52*(1+EK51)^(-0.5)*(1+EL51)^(-0.5) -> 4.2822353e-05
B55: Flat IRR Working
B57: Flat IRR
B58: i | C58: 0 | D58: 1 | E58: 2 | F58: 3 | G58: 4 | H58: 5 | I58: 6 | J58: 7 | K58: 8 | L58: 9 | M58: 10 | N58: 11 | O58: 12 | P58: 13 | Q58: 14 | R58: 15 | S58: 16 | T58: 17 | U58: 18 | V58: 19 | W58: 20 | X58: 21 | Y58: 22 | Z58: 23 | AA58: 24 | AB58: 25 | AC58: 26 | AD58: 27 | AE58: 28 | AF58: 29 | AG58: 30 | AH58: 31 | AI58: 32 | AJ58: 33 | AK58: 34 | AL58: 35 | AM58: 36 | AN58: 37 | AO58: 38 | AP58: 39 | AQ58: 40 | AR58: 41 | AS58: 42 | AT58: 43 | AU58: 44 | AV58: 45 | AW58: 46 | AX58: 47 | AY58: 48 | AZ58: 49 | BA58: 50 | BB58: 51 | BC58: 52 | BD58: 53 | BE58: 54 | BF58: 55 | BG58: 56 | BH58: 57 | BI58: 58 | BJ58: 59 | BK58: 60 | BL58: 61 | BM58: 62 | BN58: 63 | BO58: 64 | BP58: 65 | BQ58: 66 | BR58: 67 | BS58: 68 | BT58: 69 | BU58: 70 | BV58: 71 | BW58: 72 | BX58: 73 | BY58: 74 | BZ58: 75 | CA58: 76 | CB58: 77 | CC58: 78 | CD58: 79 | CE58: 80 | CF58: 81 | CG58: 82 | CH58: 83 | CI58: 84 | CJ58: 85 | CK58: 86 | CL58: 87 | CM58: 88 | CN58: 89 | CO58: 90 | CP58: 91 | CQ58: 92 | CR58: 93 | CS58: 94 | CT58: 95 | CU58: 96 | CV58: 97 | CW58: 98 | CX58: 99 | CY58: 100 | CZ58: 101 | DA58: 102 | DB58: 103 | DC58: 104 | DD58: 105 | DE58: 106 | DF58: 107 | DG58: 108 | DH58: 109 | DI58: 110 | DJ58: 111 | DK58: 112 | DL58: 113 | DM58: 114 | DN58: 115 | DO58: 116 | DP58: 117 | DQ58: 118 | DR58: 119 | DS58: 120 | DT58: 121 | DU58: 122 | DV58: 123 | DW58: 124 | DX58: 125 | DY58: 126 | DZ58: 127 | EA58: 128 | EB58: 129 | EC58: 130 | ED58: 131 | EE58: 132 | EF58: 133 | EG58: 134 | EH58: 135 | EI58: 136 | EJ58: 137 | EK58: 138 | EL58: 139
B59: Flat IRR Yield Curve | C59: =IF(OtherAssump!$C$7="Y", IF((C45-$D$45)<=30, $F$83, IF(AND((C45-$D$45)>30,(C45-$D$45)<=40), $F$83+$C$38*(C45-$D$45-30)/10, $F$83+$C$38)), $F$83) -> 0.073867569 | D59: =IF(OtherAssump!$C$7="Y", IF((D45-$D$45)<=30, $F$83, IF(AND((D45-$D$45)>30,(D45-$D$45)<=40), $F$83+$C$38*(D45-$D$45-30)/10, $F$83+$C$38)), $F$83) -> 0.073867569 | E59: =IF(OtherAssump!$C$7="Y", IF((E45-$D$45)<=30, $F$83, IF(AND((E45-$D$45)>30,(E45-$D$45)<=40), $F$83+$C$38*(E45-$D$45-30)/10, $F$83+$C$38)), $F$83) -> 0.073867569 | F59: =IF(OtherAssump!$C$7="Y", IF((F45-$D$45)<=30, $F$83, IF(AND((F45-$D$45)>30,(F45-$D$45)<=40), $F$83+$C$38*(F45-$D$45-30)/10, $F$83+$C$38)), $F$83) -> 0.073867569 | G59: =IF(OtherAssump!$C$7="Y", IF((G45-$D$45)<=30, $F$83, IF(AND((G45-$D$45)>30,(G45-$D$45)<=40), $F$83+$C$38*(G45-$D$45-30)/10, $F$83+$C$38)), $F$83) -> 0.073867569 | H59: =IF(OtherAssump!$C$7="Y", IF((H45-$D$45)<=30, $F$83, IF(AND((H45-$D$45)>30,(H45-$D$45)<=40), $F$83+$C$38*(H45-$D$45-30)/10, $F$83+$C$38)), $F$83) -> 0.073867569 | I59: =IF(OtherAssump!$C$7="Y", IF((I45-$D$45)<=30, $F$83, IF(AND((I45-$D$45)>30,(I45-$D$45)<=40), $F$83+$C$38*(I45-$D$45-30)/10, $F$83+$C$38)), $F$83) -> 0.073867569 | J59: =IF(OtherAssump!$C$7="Y", IF((J45-$D$45)<=30, $F$83, IF(AND((J45-$D$45)>30,(J45-$D$45)<=40), $F$83+$C$38*(J45-$D$45-30)/10, $F$83+$C$38)), $F$83) -> 0.073867569 | ... EL59: =IF(OtherAssump!$C$7="Y", IF((EL45-$D$45)<=30, $F$83, IF(AND((EL45-$D$45)>30,(EL45-$D$45)<=40), $F$83+$C$38*(EL45-$D$45-30)/10, $F$83+$C$38)), $F$83) -> 0.075667626
B60: Discounted Factor *Flat IRR | C60: =1 -> 1 | D60: =C60*(1+C59)^(-0.5)*(1+D59)^(-0.5) -> 0.93121352 | E60: =D60*(1+D59)^(-0.5)*(1+E59)^(-0.5) -> 0.86715862 | F60: =E60*(1+E59)^(-0.5)*(1+F59)^(-0.5) -> 0.80750983 | G60: =F60*(1+F59)^(-0.5)*(1+G59)^(-0.5) -> 0.75196407 | H60: =G60*(1+G59)^(-0.5)*(1+H59)^(-0.5) -> 0.70023911 | I60: =H60*(1+H59)^(-0.5)*(1+I59)^(-0.5) -> 0.65207213 | J60: =I60*(1+I59)^(-0.5)*(1+J59)^(-0.5) -> 0.60721838 | K60: =J60*(1+J59)^(-0.5)*(1+K59)^(-0.5) -> 0.56544997 | ... EL60: =EK60*(1+EK59)^(-0.5)*(1+EL59)^(-0.5) -> 4.196901e-05
B62: Total CF ->
B63: i | C63: =C117 -> 0 | D63: =D117 -> 1 | E63: =E117 -> 2 | F63: =F117 -> 3 | G63: =G117 -> 4 | H63: =H117 -> 5 | I63: =I117 -> 6 | J63: =J117 -> 7 | ... EL63: =EL117 -> 139
B64: Gua CF | C64: =0 -> 0 | D64: =-SUM(D105:D106,D91:D92) -> -182.39306 | E64: =-SUM(E105:E106,E91:E92) -> -184.8332 | F64: =-SUM(F105:F106,F91:F92) -> -209.57402 | G64: =-SUM(G105:G106,G91:G92) -> -231.633 | H64: =-SUM(H105:H106,H91:H92) -> -195.89805 | I64: =-SUM(I105:I106,I91:I92) -> -109.93101 | J64: =-SUM(J105:J106,J91:J92) -> -44.591991 | K64: =-SUM(K105:K106,K91:K92) -> 19.997102 | ... EL64: =-SUM(EL105:EL106,EL91:EL92) -> 0
B65: Non-Gua AD | C65: =0 -> 0 | D65: =-D93 -> 0.24255397 | E65: =-E93 -> 0.45382535 | F65: =-F93 -> 0.43965134 | G65: =-G93 -> 0.4201688 | H65: =-H93 -> 1.4083588 | I65: =-I93 -> 1.3674452 | J65: =-J93 -> 1.330748 | K65: =-K93 -> 1.297083 | ... EL65: =-EL93 -> 0
B66: Non-Gua TD | C66: =0 -> 0 | D66: =-D94-D107 -> 0.080589248 | E66: =-E94-E107 -> 0.63021953 | F66: =-F94-F107 -> 1.4487608 | G66: =-G94-G107 -> 3.3839425 | H66: =-H94-H107 -> 7.827366 | I66: =-I94-I107 -> 14.397418 | J66: =-J94-J107 -> 21.154998 | K66: =-K94-K107 -> 28.537426 | ... EL66: =-EL94-EL107 -> 0
B67: PC | C67: =0 -> 0 | D67: =-D96-D109 -> 13.519468 | E67: =-E96-E109 -> 12.492046 | F67: =-F96-F109 -> 13.720202 | G67: =-G96-G109 -> 15.172404 | H67: =-H96-H109 -> 9.2416374 | I67: =-I96-I109 -> 7.0743541 | J67: =-J96-J109 -> 5.0057175 | K67: =-K96-K109 -> 2.6230977 | ... EL67: =-EL96-EL109 -> 0
B68: AMC @ Yield Curve | C68: =0 -> 0 | D68: =-D97-D110 -> 0.972609 | E68: =-E97-E110 -> 1.3160733 | F68: =-F97-F110 -> 1.6068425 | G68: =-G97-G110 -> 1.8511894 | H68: =-H97-H110 -> 2.0524557 | I68: =-I97-I110 -> 2.1923223 | J68: =-J97-J110 -> 2.4407973 | K68: =-K97-K110 -> 8.9079667 | ... EL68: =-EL97-EL110 -> 0
B69: AMC @ Flat IRR | C69: =0 -> 0 | D69: =-D100-D113 -> 0.972609 | E69: =-E100-E113 -> 1.3161016 | F69: =-F100-F113 -> 1.6069917 | G69: =-G100-G113 -> 1.8515555 | H69: =-H100-H113 -> 2.0531201 | I69: =-I100-I113 -> 2.1930035 | J69: =-J100-J113 -> 2.4417527 | K69: =-K100-K113 -> 8.9157524 | ... EL69: =-EL100-EL113 -> 0
B71: PV of CF -> | G71: Control:
C72: @ Yield Curve | D72: @ Flat IRR | H72: @ Yield Curve | I72: @ Flat IRR
B73: AS | C73: =C98 -> 332.49053 | D73: =C101 -> 332.49053 | G73: AS | H73: =C73-'[1]3.2.2 Yield Curve_USD'!D3 -> 0 | I73: =D73-'[1]3.2.2 Yield Curve_USD'!D3 -> 0
B74: GPV | C74: =SUM(C75:C78) -> 205.40077 | D74: =SUM(D75:D78) -> 205.35365 | G74: GPV | H74: =C74-'[1]3.2.2 Yield Curve_USD'!D4 -> 0 | I74: =D74-'[1]3.2.2 Yield Curve_USD'!E4 -> 0
B75: PV of GCF | C75: =SUMPRODUCT($C$64:$EL$64,$C$52:$EL$52) -> -532.46433 | D75: =SUMPRODUCT($C$64:$EL$64,$C$60:$EL$60) -> -526.61894 | G75: PV of GCF | H75: =C75-'[1]3.2.2 Yield Curve_USD'!D5 -> 0 | I75: =D75-'[1]3.2.2 Yield Curve_USD'!E5 -> 0
B76: PV of AD | C76: =SUMPRODUCT($C$65:$EL$65,$C$52:$EL$52) -> 11.328412 | D76: =SUMPRODUCT($C$65:$EL$65,$C$60:$EL$60) -> 11.234219 | G76: PV of AD | H76: =C76-'[1]3.2.2 Yield Curve_USD'!D6 -> 0 | I76: =D76-'[1]3.2.2 Yield Curve_USD'!E6 -> 0
B77: PV of TD | C77: =SUMPRODUCT($C$66:$EL$66,$C$52:$EL$52) -> 522.73162 | D77: =SUMPRODUCT($C$66:$EL$66,$C$60:$EL$60) -> 519.04992 | G77: PV of TD | H77: =C77-'[1]3.2.2 Yield Curve_USD'!D7 -> 0 | I77: =D77-'[1]3.2.2 Yield Curve_USD'!E7 -> 0
B78: PV of SHT | C78: =SUMPRODUCT($C$67:$EL$67,$C$52:$EL$52)+ SUMPRODUCT($C$68:$EL$68,$C$52:$EL$52) -> 203.80507 | D78: =SUMPRODUCT($C$67:$EL$67,$C$60:$EL$60)+ SUMPRODUCT($C$69:$EL$69,$C$60:$EL$60) -> 201.68846 | G78: PV of SHT | H78: =C78-'[1]3.2.2 Yield Curve_USD'!D8 -> 0 | I78: =D78-'[1]3.2.2 Yield Curve_USD'!E8 -> 0
B79: Covering Ratio | C79: =(C73-C75-C77)/C76 -> 30.209287 | D79: =(D73-D75-D77)/D76 -> 30.269977
B81: Goal Seek Flat IRR ->
B82: No. | C82: Switch | D82: Method | E82: Goal | F82: Flat IRR
B83: Method 1 | C83: On | D83: Goal Seek Flat IRR such that Covering Ratio @ Yield Curve = Covering Ratio@ Flat IRR | E83: =C74-D74 -> 0.047116385 | F83: 0.073867569
B84: Method 2 | C84: Off | D84: Goal Seek Flat IRR such that GPV @ Yield Curve = GPV @ Flat IRR | E84: =C79-D79 -> -0.060690177
B87: AS Projection Calculation
B89: Existing AS Projection ->
C90: =C27 -> 0 | D90: =D27 -> 1 | E90: =E27 -> 2 | F90: =F27 -> 3 | G90: =G27 -> 4 | H90: =H27 -> 5 | I90: =I27 -> 6 | J90: =J27 -> 7 | ... EL90: =EL27 -> 139
B91: Existing AS CF Beg | D91: =LiabilityCF!D5 -> 157.1362 | E91: =LiabilityCF!E5 -> 96.610158 | F91: =LiabilityCF!F5 -> 65.549304 | G91: =LiabilityCF!G5 -> 31.393519 | H91: =LiabilityCF!H5 -> 0.58748696 | I91: =LiabilityCF!I5 -> 0.37517083 | J91: =LiabilityCF!J5 -> 0.22717929 | K91: =LiabilityCF!K5 -> 0.11492 | ... EL91: =LiabilityCF!EL5 -> 0
B92: Existing AS Gua CF End | D92: =LiabilityCF!D6 -> -8.7361245 | E92: =LiabilityCF!E6 -> -11.565252 | F92: =LiabilityCF!F6 -> -14.914699 | G92: =LiabilityCF!G6 -> -20.311022 | H92: =LiabilityCF!H6 -> -30.725002 | I92: =LiabilityCF!I6 -> -42.216237 | J92: =LiabilityCF!J6 -> -47.010825 | K92: =LiabilityCF!K6 -> -40.93181 | ... EL92: =LiabilityCF!EL6 -> 0
B93: Existing AS Non-Guar AD | D93: =LiabilityCF!D7 -> -0.24255397 | E93: =LiabilityCF!E7 -> -0.45382535 | F93: =LiabilityCF!F7 -> -0.43965134 | G93: =LiabilityCF!G7 -> -0.4201688 | H93: =LiabilityCF!H7 -> -1.4083588 | I93: =LiabilityCF!I7 -> -1.3674452 | J93: =LiabilityCF!J7 -> -1.330748 | K93: =LiabilityCF!K7 -> -1.297083 | ... EL93: =LiabilityCF!EL7 -> 0
B94: Existing AS Non-Guar TD | D94: =LiabilityCF!D8 -> -0.080589248 | E94: =LiabilityCF!E8 -> -0.2614782 | F94: =LiabilityCF!F8 -> -0.62631891 | G94: =LiabilityCF!G8 -> -1.8656562 | H94: =LiabilityCF!H8 -> -5.5287108 | I94: =LiabilityCF!I8 -> -10.494271 | J94: =LiabilityCF!J8 -> -13.551517 | K94: =LiabilityCF!K8 -> -13.726686 | ... EL94: =LiabilityCF!EL8 -> 0
B95: Existing - Int_on_asset share @ Yield Curve | D95: =C98*C$51+SUM(D91:D94,D96)*((1+C$51)^0.5-1) -> 27.06227 | E95: =D98*D$51+SUM(E91:E94,E96)*((1+D$51)^0.5-1) -> 37.058769 | F95: =E98*E$51+SUM(F91:F94,F96)*((1+E$51)^0.5-1) -> 45.113308 | G95: =F98*F$51+SUM(G91:G94,G96)*((1+F$51)^0.5-1) -> 51.144508 | H95: =G98*G$51+SUM(H91:H94,H96)*((1+G$51)^0.5-1) -> 54.980593 | I95: =H98*H$51+SUM(I91:I94,I96)*((1+H$51)^0.5-1) -> 55.40468 | J95: =I98*I$51+SUM(J91:J94,J96)*((1+I$51)^0.5-1) -> 55.283868 | K95: =J98*J$51+SUM(K91:K94,K96)*((1+J$51)^0.5-1) -> 54.847258 | ... EL95: =EK98*EK$51+SUM(EL91:EL94,EL96)*((1+EK$51)^0.5-1) -> 78072.995
B96: Existing PC | D96: =LiabilityCF!D9 -> -9.2345383 | E96: =LiabilityCF!E9 -> -5.1722488 | F96: =LiabilityCF!F9 -> -3.3489432 | G96: =LiabilityCF!G9 -> -1.6162146 | H96: =LiabilityCF!H9 -> -0.0023959212 | I96: =LiabilityCF!I9 -> 0 | J96: =LiabilityCF!J9 -> 0 | K96: =LiabilityCF!K9 -> 0 | ... EL96: =LiabilityCF!EL9 -> 0
B97: Existing AMC @ Yield Curve | D97: =LiabilityCF!D10 -> -0.96921908 | E97: =LiabilityCF!E10 -> -1.2922209 | F97: =LiabilityCF!F10 -> -1.5408614 | G97: =LiabilityCF!G10 -> -1.7148611 | H97: =LiabilityCF!H10 -> -1.8019294 | I97: =LiabilityCF!I10 -> -1.819106 | J97: =LiabilityCF!J10 -> -1.8043699 | K97: =LiabilityCF!K10 -> -1.7928081 | ... EL97: =LiabilityCF!EL10 -> 0
B98: Existing Ending AS @ Yield Curve | C98: =OtherAssump!$C$9 -> 332.49053 | D98: =C98+SUM(D91:D97) -> 497.42598 | E98: =D98+SUM(E91:E97) -> 612.34988 | F98: =E98+SUM(F91:F97) -> 702.14202 | G98: =F98+SUM(G91:G97) -> 758.75212 | H98: =G98+SUM(H91:H97) -> 774.8538 | I98: =H98+SUM(I91:I97) -> 774.7366 | J98: =I98+SUM(J91:J97) -> 766.55018 | K98: =J98+SUM(K91:K97) -> 763.76397 | ... EL98: =EK98+SUM(EL91:EL97) -> 1111821.4
B99: Existing - Int_on_asset share @ Flat IRR | D99: =C101*C$59+SUM(D91:D94,D96)*((1+C$59)^0.5-1) -> 29.596889 | E99: =D101*D$59+SUM(E91:E94,E96)*((1+D$59)^0.5-1) -> 39.802372 | F99: =E101*E$59+SUM(F91:F94,F96)*((1+E$59)^0.5-1) -> 47.112117 | G99: =F101*F$59+SUM(G91:G94,G96)*((1+F$59)^0.5-1) -> 52.273648 | H99: =G101*G$59+SUM(H91:H94,H96)*((1+G$59)^0.5-1) -> 54.785584 | I99: =H101*H$59+SUM(I91:I94,I96)*((1+H$59)^0.5-1) -> 55.27405 | J99: =I101*I$59+SUM(J91:J94,J96)*((1+I$59)^0.5-1) -> 54.981279 | K99: =J101*J$59+SUM(K91:K94,K96)*((1+J$59)^0.5-1) -> 54.575182 | ... EL99: =EK101*EK$59+SUM(EL91:EL94,EL96)*((1+EK$59)^0.5-1) -> 78232.511
B100: Existing AMC @ Flat IRR | D100: =D97 -> -0.96921908 | E100: =E97 -> -1.2922209 | F100: =F97 -> -1.5408614 | G100: =G97 -> -1.7148611 | H100: =H97 -> -1.8019294 | I100: =I97 -> -1.819106 | J100: =J97 -> -1.8043699 | K100: =K97 -> -1.7928081 | ... EL100: =EL97 -> 0
B101: Existing Ending AS @ Flat IRR | C101: =OtherAssump!$C$9 -> 332.49053 | D101: =D98-D95-D97+SUM(D99:D100) -> 499.9606 | E101: =E98-E95-E97+SUM(E99:E100) -> 615.09348 | F101: =F98-F95-F97+SUM(F99:F100) -> 704.14083 | G101: =G98-G95-G97+SUM(G99:G100) -> 759.88126 | H101: =H98-H95-H97+SUM(H99:H100) -> 774.65879 | I101: =I98-I95-I97+SUM(I99:I100) -> 774.60597 | J101: =J98-J95-J97+SUM(J99:J100) -> 766.24759 | K101: =K98-K95-K97+SUM(K99:K100) -> 763.4919 | ... EL101: =EL98-EL95-EL97+SUM(EL99:EL100) -> 1111980.9
B103: NB AS Projection ->
B104: i | C104: =C90 -> 0 | D104: =D90 -> 1 | E104: =E90 -> 2 | F104: =F90 -> 3 | G104: =G90 -> 4 | H104: =H90 -> 5 | I104: =I90 -> 6 | J104: =J90 -> 7 | ... EL104: =EL90 -> 139
B105: NB Inflow | D105: =LiabilityCF!D18*OtherAssump!$C$8 -> 79.945 | E105: =LiabilityCF!E18*OtherAssump!$C$8 -> 158.28781 | F105: =LiabilityCF!F18*OtherAssump!$C$8 -> 228.17772 | G105: =LiabilityCF!G18*OtherAssump!$C$8 -> 300.39462 | H105: =LiabilityCF!H18*OtherAssump!$C$8 -> 241.33982 | I105: =LiabilityCF!I18*OtherAssump!$C$8 -> 169.73675 | J105: =LiabilityCF!J18*OtherAssump!$C$8 -> 119.55037 | K105: =LiabilityCF!K18*OtherAssump!$C$8 -> 65.074757 | ... EL105: =LiabilityCF!EL18*OtherAssump!$C$8 -> 0
B106: NB Gua Outflow | D106: =LiabilityCF!D19*OtherAssump!$C$8 -> -45.952014 | E106: =LiabilityCF!E19*OtherAssump!$C$8 -> -58.499508 | F106: =LiabilityCF!F19*OtherAssump!$C$8 -> -69.238308 | G106: =LiabilityCF!G19*OtherAssump!$C$8 -> -79.844118 | H106: =LiabilityCF!H19*OtherAssump!$C$8 -> -15.304253 | I106: =LiabilityCF!I19*OtherAssump!$C$8 -> -17.964666 | J106: =LiabilityCF!J19*OtherAssump!$C$8 -> -28.174728 | K106: =LiabilityCF!K19*OtherAssump!$C$8 -> -44.254969 | ... EL106: =LiabilityCF!EL19*OtherAssump!$C$8 -> 0
B107: NB Non-Gua Outflow | D107: =LiabilityCF!D20*OtherAssump!$C$8 -> 0 | E107: =LiabilityCF!E20*OtherAssump!$C$8 -> -0.36874133 | F107: =LiabilityCF!F20*OtherAssump!$C$8 -> -0.82244193 | G107: =LiabilityCF!G20*OtherAssump!$C$8 -> -1.5182864 | H107: =LiabilityCF!H20*OtherAssump!$C$8 -> -2.2986552 | I107: =LiabilityCF!I20*OtherAssump!$C$8 -> -3.9031472 | J107: =LiabilityCF!J20*OtherAssump!$C$8 -> -7.6034809 | K107: =LiabilityCF!K20*OtherAssump!$C$8 -> -14.81074 | ... EL107: =LiabilityCF!EL20*OtherAssump!$C$8 -> 0
B108: NB - Int_on_asset share @ Yield Curve | D108: =IF(LiabilityCF!D22=0,0,C111*C51+SUM(D105:D107,D109)*((1+C51)^0.5-1)) -> 0.98662568 | E108: =IF(LiabilityCF!E22=0,0,D111*D51+SUM(E105:E107,E109)*((1+D51)^0.5-1)) -> 5.2493048 | F108: =IF(LiabilityCF!F22=0,0,E111*E51+SUM(F105:F107,F109)*((1+E51)^0.5-1)) -> 14.251689 | G108: =IF(LiabilityCF!G22=0,0,F111*F51+SUM(G105:G107,G109)*((1+F51)^0.5-1)) -> 28.330295 | H108: =IF(LiabilityCF!H22=0,0,G111*G51+SUM(H105:H107,H109)*((1+G51)^0.5-1)) -> 46.695126 | I108: =IF(LiabilityCF!I22=0,0,H111*H51+SUM(I105:I107,I109)*((1+H51)^0.5-1)) -> 63.193287 | J108: =IF(LiabilityCF!J22=0,0,I111*I51+SUM(J105:J107,J109)*((1+I51)^0.5-1)) -> 76.254898 | K108: =IF(LiabilityCF!K22=0,0,J111*J51+SUM(K105:K107,K109)*((1+J51)^0.5-1)) -> 84.90727 | ... EL108: =IF(LiabilityCF!EL22=0,0,EK111*EK51+SUM(EL105:EL107,EL109)*((1+EK51)^0.5-1)) -> 0
B109: NB - PC | D109: =LiabilityCF!D21*OtherAssump!$C$8 -> -4.28493 | E109: =LiabilityCF!E21*OtherAssump!$C$8 -> -7.3197967 | F109: =LiabilityCF!F21*OtherAssump!$C$8 -> -10.371259 | G109: =LiabilityCF!G21*OtherAssump!$C$8 -> -13.556189 | H109: =LiabilityCF!H21*OtherAssump!$C$8 -> -9.2392415 | I109: =LiabilityCF!I21*OtherAssump!$C$8 -> -7.0743541 | J109: =LiabilityCF!J21*OtherAssump!$C$8 -> -5.0057175 | K109: =LiabilityCF!K21*OtherAssump!$C$8 -> -2.6230977 | ... EL109: =LiabilityCF!EL21*OtherAssump!$C$8 -> 0
B110: NB - AMC @ Yield Curve | D110: =MIN(0,-C111*LiabilityCF!D22-SUM(D105:D107,D109)/2*LiabilityCF!D22) -> -0.0033899194 | E110: =MIN(0,-D111*LiabilityCF!E22-SUM(E105:E107,E109)/2*LiabilityCF!E22) -> -0.023852396 | F110: =MIN(0,-E111*LiabilityCF!F22-SUM(F105:F107,F109)/2*LiabilityCF!F22) -> -0.065981046 | G110: =MIN(0,-F111*LiabilityCF!G22-SUM(G105:G107,G109)/2*LiabilityCF!G22) -> -0.13632831 | H110: =MIN(0,-G111*LiabilityCF!H22-SUM(H105:H107,H109)/2*LiabilityCF!H22) -> -0.25052629 | I110: =MIN(0,-H111*LiabilityCF!I22-SUM(I105:I107,I109)/2*LiabilityCF!I22) -> -0.37321631 | J110: =MIN(0,-I111*LiabilityCF!J22-SUM(J105:J107,J109)/2*LiabilityCF!J22) -> -0.63642741 | K110: =MIN(0,-J111*LiabilityCF!K22-SUM(K105:K107,K109)/2*LiabilityCF!K22) -> -7.1151586 | ... EL110: =MIN(0,-EK111*LiabilityCF!EL22-SUM(EL105:EL107,EL109)/2*LiabilityCF!EL22) -> 0
B111: NB Ending AS @ Yield Curve | D111: =C111+SUM(D105:D110) -> 30.691292 | E111: =D111+SUM(E105:E110) -> 128.0165 | F111: =E111+SUM(F105:F110) -> 289.94793 | G111: =F111+SUM(G105:G110) -> 523.61792 | H111: =G111+SUM(H105:H110) -> 784.56019 | I111: =H111+SUM(I105:I110) -> 988.17484 | J111: =I111+SUM(J105:J110) -> 1142.5597 | K111: =J111+SUM(K105:K110) -> 1223.7378 | ... EL111: =EK111+SUM(EL105:EL110) -> 108422.92
B112: NB - Int_on_asset share @ Flat IRR | D112: =IF(LiabilityCF!D22=0,0,C114*C59+SUM(D105:D107,D109)*((1+C59)^0.5-1)) -> 1.077684 | E112: =IF(LiabilityCF!E22=0,0,D114*D59+SUM(E105:E107,E109)*((1+D59)^0.5-1)) -> 5.6148115 | F112: =IF(LiabilityCF!F22=0,0,E114*E59+SUM(F105:F107,F109)*((1+E59)^0.5-1)) -> 14.849588 | G112: =IF(LiabilityCF!G22=0,0,F114*F59+SUM(G105:G107,G109)*((1+F59)^0.5-1)) -> 28.949437 | H112: =IF(LiabilityCF!H22=0,0,G114*G59+SUM(H105:H107,H109)*((1+G59)^0.5-1)) -> 46.583046 | I112: =IF(LiabilityCF!I22=0,0,H114*H59+SUM(I105:I107,I109)*((1+H59)^0.5-1)) -> 63.176249 | J112: =IF(LiabilityCF!J22=0,0,I114*I59+SUM(J105:J107,J109)*((1+I59)^0.5-1)) -> 75.965338 | K112: =IF(LiabilityCF!K22=0,0,J114*J59+SUM(K105:K107,K109)*((1+J59)^0.5-1)) -> 84.613428 | ... EL112: =IF(LiabilityCF!EL22=0,0,EK114*EK59+SUM(EL105:EL107,EL109)*((1+EK59)^0.5-1)) -> 0
B113: NB AMC @ Flat IRR | D113: =MIN(0,-C114*LiabilityCF!D22-SUM(D105:D107,D109)/2*LiabilityCF!D22) -> -0.0033899194 | E113: =MIN(0,-D114*LiabilityCF!E22-SUM(E105:E107,E109)/2*LiabilityCF!E22) -> -0.023880698 | F113: =MIN(0,-E114*LiabilityCF!F22-SUM(F105:F107,F109)/2*LiabilityCF!F22) -> -0.06613025 | G113: =MIN(0,-F114*LiabilityCF!G22-SUM(G105:G107,G109)/2*LiabilityCF!G22) -> -0.13669432 | H113: =MIN(0,-G114*LiabilityCF!H22-SUM(H105:H107,H109)/2*LiabilityCF!H22) -> -0.25119069 | I113: =MIN(0,-H114*LiabilityCF!I22-SUM(I105:I107,I109)/2*LiabilityCF!I22) -> -0.37389744 | J113: =MIN(0,-I114*LiabilityCF!J22-SUM(J105:J107,J109)/2*LiabilityCF!J22) -> -0.63738283 | K113: =MIN(0,-J114*LiabilityCF!K22-SUM(K105:K107,K109)/2*LiabilityCF!K22) -> -7.1229443 | ... EL113: =MIN(0,-EK114*LiabilityCF!EL22-SUM(EL105:EL107,EL109)/2*LiabilityCF!EL22) -> 0
B114: NB Ending AS @ Flat IRR | D114: =C114+SUM(D105:D107,D109,D112:D113) -> 30.78235 | E114: =D114+SUM(E105:E107,E109,E112:E113) -> 128.47304 | F114: =E114+SUM(F105:F107,F109,F112:F113) -> 291.00221 | G114: =F114+SUM(G105:G107,G109,G112:G113) -> 525.29098 | H114: =G114+SUM(H105:H107,H109,H112:H113) -> 786.12051 | I114: =H114+SUM(I105:I107,I109,I112:I113) -> 989.71744 | J114: =I114+SUM(J105:J107,J109,J112:J113) -> 1143.8118 | K114: =J114+SUM(K105:K107,K109,K112:K113) -> 1224.6883 | ... EL114: =EK114+SUM(EL105:EL107,EL109,EL112:EL113) -> 107798.25
B116: Ending AS ->
B117: i | C117: =C104 -> 0 | D117: =D104 -> 1 | E117: =E104 -> 2 | F117: =F104 -> 3 | G117: =G104 -> 4 | H117: =H104 -> 5 | I117: =I104 -> 6 | J117: =J104 -> 7 | ... EL117: =EL104 -> 139
B118: Ending AS @ Yield Curve | C118: =C98+C111 -> 332.49053 | D118: =D98+D111 -> 528.11727 | E118: =E98+E111 -> 740.36638 | F118: =F98+F111 -> 992.08994 | G118: =G98+G111 -> 1282.37 | H118: =H98+H111 -> 1559.414 | I118: =I98+I111 -> 1762.9114 | J118: =J98+J111 -> 1909.1099 | ... EL118: =EL98+EL111 -> 1220244.3
B119: Ending AS @ Flat IRR | C119: =C101+C114 -> 332.49053 | D119: =D101+D114 -> 530.74295 | E119: =E101+E114 -> 743.56652 | F119: =F101+F114 -> 995.14304 | G119: =G101+G114 -> 1285.1722 | H119: =H101+H114 -> 1560.7793 | I119: =I101+I114 -> 1764.3234 | J119: =J101+J114 -> 1910.0594 | ... EL119: =EL101+EL114 -> 1219779.2

Sheet Input Table ->

Sheet AssetAssump
A3: AssetAssump
B5: Asset Type 1 | C5: Asset Type 2 | D5: Asset Mix | E5: Asset Return
B6: Bond | C6: AC Bond | D6: 0 | E6: 0
B7: Bond | C7: IG_Tradable-ST | D7: 0.027064772 | E7: 0.0343
B8: Bond | C8: IG_Tradable-10Y | D8: 0.10685131 | E8: 0.0437
B9: Bond | C9: IG_Tradable-LT | D9: 0.26062942 | E9: 0.0518
B10: Bond | C10: HY | D10: 0 | E10: 0.0683
B11: Bond | C11: Securitized - CMBS | D11: 0 | E11: 0.0415
B12: Equity | C12: DM | D12: 0.17126599 | E12: 0.0806
B13: Equity | C13: EM | D13: 0.17126599 | E13: 0.0962
B14: Alternatives | C14: PE | D14: 0.14 | E14: 0.107
B15: Alternatives | C15: Loan/Private Credit | D15: 0.09 | E15: 0.077
B16: Alternatives | C16: Property | D16: 0.02 | E16: 0.073
B17: Alternatives | C17: Hedging Fund | D17: 0 | E17: 0.051
... B26: Others | C26: Seed Capital | D26: 0 | E26: 0.02
C27: Other Asset | D27: 0.012922511 | E27: 0
B28: Others | C28: Policy Loan | D28: 0 | E28: 0.075

Sheet InititalAssetMix
A2: InititalAssetMix
B4: Asset | C4: Asset Mix
B5: Bond | C5: 0.5109
B6: Equity | C6: 0.4151
B7: Alternatives | C7: 0.0523
B8: Others | C8: 0.0010358475

Sheet OtherAssump
A2: OtherAssump
B4: Variable | C4: Value
B5: Calendar Year | C5: 45657
B6: IA_RF_YR150 | C6: 0.037562355
B7: Interpolation | C7: Y
B8: NB mix | C8: 1
B9: Beg AS | C9: 332.49053
B10: HKD Yield Shock | C10: 0
B11: Bond Reinvestment Yield Method | C11: Bond Reinvestment Yield Method 1

Sheet ExisitngBond
A2: ExisitngBondYield
B4: BondCat | C4: 0 | D4: 1 | E4: 2 | F4: 3 | G4: 4 | H4: 5 | I4: 6 | J4: 7 | K4: 8 | L4: 9 | M4: 10 | N4: 11 | O4: 12 | P4: 13 | Q4: 14 | R4: 15 | S4: 16 | T4: 17 | U4: 18 | V4: 19 | W4: 20 | X4: 21 | Y4: 22 | Z4: 23 | AA4: 24 | AB4: 25 | AC4: 26 | AD4: 27 | AE4: 28 | AF4: 29 | AG4: 30 | AH4: 31 | AI4: 32 | AJ4: 33 | AK4: 34 | AL4: 35 | AM4: 36 | AN4: 37 | AO4: 38 | AP4: 39 | AQ4: 40 | AR4: 41 | AS4: 42 | AT4: 43 | AU4: 44 | AV4: 45 | AW4: 46 | AX4: 47 | AY4: 48 | AZ4: 49 | BA4: 50 | BB4: 51 | BC4: 52 | BD4: 53 | BE4: 54 | BF4: 55 | BG4: 56 | BH4: 57 | BI4: 58 | BJ4: 59 | BK4: 60 | BL4: 61 | BM4: 62 | BN4: 63 | BO4: 64 | BP4: 65 | BQ4: 66 | BR4: 67 | BS4: 68 | BT4: 69 | BU4: 70 | BV4: 71 | BW4: 72 | BX4: 73 | BY4: 74 | BZ4: 75 | CA4: 76 | CB4: 77 | CC4: 78 | CD4: 79 | CE4: 80 | CF4: 81 | CG4: 82 | CH4: 83 | CI4: 84 | CJ4: 85 | CK4: 86 | CL4: 87 | CM4: 88 | CN4: 89 | CO4: 90 | CP4: 91 | CQ4: 92 | CR4: 93 | CS4: 94 | CT4: 95 | CU4: 96 | CV4: 97 | CW4: 98 | CX4: 99 | CY4: 100 | CZ4: 101 | DA4: 102 | DB4: 103 | DC4: 104 | DD4: 105 | DE4: 106 | DF4: 107 | DG4: 108 | DH4: 109 | DI4: 110 | DJ4: 111 | DK4: 112 | DL4: 113 | DM4: 114 | DN4: 115 | DO4: 116 | DP4: 117 | DQ4: 118 | DR4: 119 | DS4: 120 | DT4: 121 | DU4: 122 | DV4: 123 | DW4: 124 | DX4: 125 | DY4: 126 | DZ4: 127 | EA4: 128 | EB4: 129 | EC4: 130 | ED4: 131 | EE4: 132 | EF4: 133 | EG4: 134 | EH4: 135 | EI4: 136 | EJ4: 137 | EK4: 138 | EL4: 139
B5: IG_Others | C5: 0.048043055 | D5: 0.048043055 | E5: 0.049711456 | F5: 0.049856755 | G5: 0.052259553 | H5: 0.051185394 | I5: 0.053872841 | J5: 0.053715969 | K5: 0.052437052 | L5: 0.056987299 | M5: 0.054232663 | N5: 0.054993282 | O5: 0.057087028 | P5: 0.058617229 | Q5: 0.059632239 | R5: 0.060135743 | S5: 0.060123966 | T5: 0.059697232 | U5: 0.058962107 | V5: 0.057903199 | W5: 0.05637764 | X5: 0.054421531 | Y5: 0.05265879 | Z5: 0.051110433 | AA5: 0.049886907 | AB5: 0.048835909 | AC5: 0.048220408 | AD5: 0.047593084 | AE5: 0.046613885 | AF5: 0.045347565 | AG5: 0.045439316 | AH5: 0.044673517 | AI5: 0.044622224 | AJ5: 0.044651239 | AK5: 0.044671168 | AL5: 0.044470992 | AM5: 0.04513096 | AN5: 0.044711977 | AO5: 0.044153044 | AP5: 0.041986915 | AQ5: 0.040785614 | AR5: 0.040815722 | AS5: 0.040835992 | AT5: 0.040947229 | AU5: 0.039912543 | AV5: 0.039775433 | AW5: 0.03948465 | AX5: 0.039507661 | AY5: N/A | AZ5: N/A | BA5: N/A | BB5: 0 | BC5: 0 | BD5: 0 | BE5: 0 | BF5: 0 | BG5: 0 | BH5: 0 | BI5: 0 | BJ5: 0 | BK5: 0 | BL5: 0 | BM5: 0 | BN5: 0 | BO5: 0 | BP5: 0 | BQ5: 0 | BR5: 0 | BS5: 0 | BT5: 0 | BU5: 0 | BV5: 0 | BW5: 0 | BX5: 0 | BY5: 0 | BZ5: 0 | CA5: 0 | CB5: 0 | CC5: 0 | CD5: 0 | CE5: 0 | CF5: 0 | CG5: 0 | CH5: 0 | CI5: 0 | CJ5: 0 | CK5: 0 | CL5: 0 | CM5: 0 | CN5: 0 | CO5: 0 | CP5: 0 | CQ5: 0 | CR5: 0 | CS5: 0 | CT5: 0 | CU5: 0 | CV5: 0 | CW5: 0 | CX5: 0 | CY5: 0 | CZ5: 0 | DA5: 0 | DB5: 0 | DC5: 0 | DD5: 0 | DE5: 0 | DF5: 0 | DG5: 0 | DH5: 0 | DI5: 0 | DJ5: 0 | DK5: 0 | DL5: 0 | DM5: 0 | DN5: 0 | DO5: 0 | DP5: 0 | DQ5: 0 | DR5: 0 | DS5: 0 | DT5: 0 | DU5: 0 | DV5: 0 | DW5: 0 | DX5: 0 | DY5: 0 | DZ5: 0 | EA5: 0 | EB5: 0 | EC5: 0 | ED5: 0 | EE5: 0 | EF5: 0 | EG5: 0 | EH5: 0 | EI5: 0 | EJ5: 0 | EK5: 0 | EL5: 0
B6: IG_AC | C6: 0 | D6: 0 | E6: 0 | F6: 0 | G6: 0 | H6: 0 | I6: 0 | J6: 0 | K6: 0 | L6: 0 | M6: 0 | N6: 0 | O6: 0 | P6: 0 | Q6: 0 | R6: 0 | S6: 0 | T6: 0 | U6: 0 | V6: 0 | W6: 0 | X6: 0 | Y6: 0 | Z6: 0 | AA6: 0 | AB6: 0 | AC6: 0 | AD6: 0 | AE6: 0 | AF6: 0 | AG6: 0 | AH6: 0 | AI6: 0 | AJ6: 0 | AK6: 0 | AL6: 0 | AM6: 0 | AN6: 0 | AO6: 0 | AP6: 0 | AQ6: 0 | AR6: 0 | AS6: 0 | AT6: 0 | AU6: 0 | AV6: 0 | AW6: 0 | AX6: 0 | AY6: 0 | AZ6: 0 | BA6: 0 | BB6: 0 | BC6: 0 | BD6: 0 | BE6: 0 | BF6: 0 | BG6: 0 | BH6: 0 | BI6: 0 | BJ6: 0 | BK6: 0 | BL6: 0 | BM6: 0 | BN6: 0 | BO6: 0 | BP6: 0 | BQ6: 0 | BR6: 0 | BS6: 0 | BT6: 0 | BU6: 0 | BV6: 0 | BW6: 0 | BX6: 0 | BY6: 0 | BZ6: 0 | CA6: 0 | CB6: 0 | CC6: 0 | CD6: 0 | CE6: 0 | CF6: 0 | CG6: 0 | CH6: 0 | CI6: 0 | CJ6: 0 | CK6: 0 | CL6: 0 | CM6: 0 | CN6: 0 | CO6: 0 | CP6: 0 | CQ6: 0 | CR6: 0 | CS6: 0 | CT6: 0 | CU6: 0 | CV6: 0 | CW6: 0 | CX6: 0 | CY6: 0 | CZ6: 0 | DA6: 0 | DB6: 0 | DC6: 0 | DD6: 0 | DE6: 0 | DF6: 0 | DG6: 0 | DH6: 0 | DI6: 0 | DJ6: 0 | DK6: 0 | DL6: 0 | DM6: 0 | DN6: 0 | DO6: 0 | DP6: 0 | DQ6: 0 | DR6: 0 | DS6: 0 | DT6: 0 | DU6: 0 | DV6: 0 | DW6: 0 | DX6: 0 | DY6: 0 | DZ6: 0 | EA6: 0 | EB6: 0 | EC6: 0 | ED6: 0 | EE6: 0 | EF6: 0 | EG6: 0 | EH6: 0 | EI6: 0 | EJ6: 0 | EK6: 0 | EL6: 0
B7: HY | C7: 0 | D7: 0 | E7: 0 | F7: 0 | G7: 0 | H7: 0 | I7: 0 | J7: 0 | K7: 0 | L7: 0 | M7: 0 | N7: 0 | O7: 0 | P7: 0 | Q7: 0 | R7: 0 | S7: 0 | T7: 0 | U7: 0 | V7: 0 | W7: 0 | X7: 0 | Y7: 0 | Z7: 0 | AA7: 0 | AB7: 0 | AC7: 0 | AD7: 0 | AE7: 0 | AF7: 0 | AG7: 0 | AH7: 0 | AI7: 0 | AJ7: 0 | AK7: 0 | AL7: 0 | AM7: 0 | AN7: 0 | AO7: 0 | AP7: 0 | AQ7: 0 | AR7: 0 | AS7: 0 | AT7: 0 | AU7: 0 | AV7: 0 | AW7: 0 | AX7: 0 | AY7: 0 | AZ7: 0 | BA7: 0 | BB7: 0 | BC7: 0 | BD7: 0 | BE7: 0 | BF7: 0 | BG7: 0 | BH7: 0 | BI7: 0 | BJ7: 0 | BK7: 0 | BL7: 0 | BM7: 0 | BN7: 0 | BO7: 0 | BP7: 0 | BQ7: 0 | BR7: 0 | BS7: 0 | BT7: 0 | BU7: 0 | BV7: 0 | BW7: 0 | BX7: 0 | BY7: 0 | BZ7: 0 | CA7: 0 | CB7: 0 | CC7: 0 | CD7: 0 | CE7: 0 | CF7: 0 | CG7: 0 | CH7: 0 | CI7: 0 | CJ7: 0 | CK7: 0 | CL7: 0 | CM7: 0 | CN7: 0 | CO7: 0 | CP7: 0 | CQ7: 0 | CR7: 0 | CS7: 0 | CT7: 0 | CU7: 0 | CV7: 0 | CW7: 0 | CX7: 0 | CY7: 0 | CZ7: 0 | DA7: 0 | DB7: 0 | DC7: 0 | DD7: 0 | DE7: 0 | DF7: 0 | DG7: 0 | DH7: 0 | DI7: 0 | DJ7: 0 | DK7: 0 | DL7: 0 | DM7: 0 | DN7: 0 | DO7: 0 | DP7: 0 | DQ7: 0 | DR7: 0 | DS7: 0 | DT7: 0 | DU7: 0 | DV7: 0 | DW7: 0 | DX7: 0 | DY7: 0 | DZ7: 0 | EA7: 0 | EB7: 0 | EC7: 0 | ED7: 0 | EE7: 0 | EF7: 0 | EG7: 0 | EH7: 0 | EI7: 0 | EJ7: 0 | EK7: 0 | EL7: 0
B8: Overall Bond Yield | C8: 0.048043055 | D8: 0.048043055 | E8: 0.049711456 | F8: 0.049856755 | G8: 0.052259553 | H8: 0.051185394 | I8: 0.053872841 | J8: 0.053715969 | K8: 0.052437052 | L8: 0.056987299 | M8: 0.054232663 | N8: 0.054993282 | O8: 0.057087028 | P8: 0.058617229 | Q8: 0.059632239 | R8: 0.060135743 | S8: 0.060123966 | T8: 0.059697232 | U8: 0.058962107 | V8: 0.057903199 | W8: 0.05637764 | X8: 0.054421531 | Y8: 0.05265879 | Z8: 0.051110433 | AA8: 0.049886907 | AB8: 0.048835909 | AC8: 0.048220408 | AD8: 0.047593084 | AE8: 0.046613885 | AF8: 0.045347565 | AG8: 0.045439316 | AH8: 0.044673517 | AI8: 0.044622224 | AJ8: 0.044651239 | AK8: 0.044671168 | AL8: 0.044470992 | AM8: 0.04513096 | AN8: 0.044711977 | AO8: 0.044153044 | AP8: 0.041986915 | AQ8: 0.040785614 | AR8: 0.040815722 | AS8: 0.040835992 | AT8: 0.040947229 | AU8: 0.039912543 | AV8: 0.039775433 | AW8: 0.03948465 | AX8: 0.039507661 | AY8: 0 | AZ8: 0 | BA8: 0 | BB8: 0 | BC8: 0 | BD8: 0 | BE8: 0 | BF8: 0 | BG8: 0 | BH8: 0 | BI8: 0 | BJ8: 0 | BK8: 0 | BL8: 0 | BM8: 0 | BN8: 0 | BO8: 0 | BP8: 0 | BQ8: 0 | BR8: 0 | BS8: 0 | BT8: 0 | BU8: 0 | BV8: 0 | BW8: 0 | BX8: 0 | BY8: 0 | BZ8: 0 | CA8: 0 | CB8: 0 | CC8: 0 | CD8: 0 | CE8: 0 | CF8: 0 | CG8: 0 | CH8: 0 | CI8: 0 | CJ8: 0 | CK8: 0 | CL8: 0 | CM8: 0 | CN8: 0 | CO8: 0 | CP8: 0 | CQ8: 0 | CR8: 0 | CS8: 0 | CT8: 0 | CU8: 0 | CV8: 0 | CW8: 0 | CX8: 0 | CY8: 0 | CZ8: 0 | DA8: 0 | DB8: 0 | DC8: 0 | DD8: 0 | DE8: 0 | DF8: 0 | DG8: 0 | DH8: 0 | DI8: 0 | DJ8: 0 | DK8: 0 | DL8: 0 | DM8: 0 | DN8: 0 | DO8: 0 | DP8: 0 | DQ8: 0 | DR8: 0 | DS8: 0 | DT8: 0 | DU8: 0 | DV8: 0 | DW8: 0 | DX8: 0 | DY8: 0 | DZ8: 0 | EA8: 0 | EB8: 0 | EC8: 0 | ED8: 0 | EE8: 0 | EF8: 0 | EG8: 0 | EH8: 0 | EI8: 0 | EJ8: 0 | EK8: 0 | EL8: 0
A11: ExistingBondAmount
B13: BondCat | C13: 0 | D13: 1 | E13: 2 | F13: 3 | G13: 4 | H13: 5 | I13: 6 | J13: 7 | K13: 8 | L13: 9 | M13: 10 | N13: 11 | O13: 12 | P13: 13 | Q13: 14 | R13: 15 | S13: 16 | T13: 17 | U13: 18 | V13: 19 | W13: 20 | X13: 21 | Y13: 22 | Z13: 23 | AA13: 24 | AB13: 25 | AC13: 26 | AD13: 27 | AE13: 28 | AF13: 29 | AG13: 30 | AH13: 31 | AI13: 32 | AJ13: 33 | AK13: 34 | AL13: 35 | AM13: 36 | AN13: 37 | AO13: 38 | AP13: 39 | AQ13: 40 | AR13: 41 | AS13: 42 | AT13: 43 | AU13: 44 | AV13: 45 | AW13: 46 | AX13: 47 | AY13: 48 | AZ13: 49 | BA13: 50 | BB13: 51 | BC13: 52 | BD13: 53 | BE13: 54 | BF13: 55 | BG13: 56 | BH13: 57 | BI13: 58 | BJ13: 59 | BK13: 60 | BL13: 61 | BM13: 62 | BN13: 63 | BO13: 64 | BP13: 65 | BQ13: 66 | BR13: 67 | BS13: 68 | BT13: 69 | BU13: 70 | BV13: 71 | BW13: 72 | BX13: 73 | BY13: 74 | BZ13: 75 | CA13: 76 | CB13: 77 | CC13: 78 | CD13: 79 | CE13: 80 | CF13: 81 | CG13: 82 | CH13: 83 | CI13: 84 | CJ13: 85 | CK13: 86 | CL13: 87 | CM13: 88 | CN13: 89 | CO13: 90 | CP13: 91 | CQ13: 92 | CR13: 93 | CS13: 94 | CT13: 95 | CU13: 96 | CV13: 97 | CW13: 98 | CX13: 99 | CY13: 100 | CZ13: 101 | DA13: 102 | DB13: 103 | DC13: 104 | DD13: 105 | DE13: 106 | DF13: 107 | DG13: 108 | DH13: 109 | DI13: 110 | DJ13: 111 | DK13: 112 | DL13: 113 | DM13: 114 | DN13: 115 | DO13: 116 | DP13: 117 | DQ13: 118 | DR13: 119 | DS13: 120 | DT13: 121 | DU13: 122 | DV13: 123 | DW13: 124 | DX13: 125 | DY13: 126 | DZ13: 127 | EA13: 128 | EB13: 129 | EC13: 130 | ED13: 131 | EE13: 132 | EF13: 133 | EG13: 134 | EH13: 135 | EI13: 136 | EJ13: 137 | EK13: 138 | EL13: 139
B14: IG_Others | C14: 178.08972 | D14: 177.16346 | E14: 177.64554 | F14: 177.79139 | G14: 178.29718 | H14: 178.43354 | I14: 178.3223 | J14: 179.09456 | K14: 179.60815 | L14: 174.52462 | M14: 163.68689 | N14: 160.22363 | O14: 159.09711 | P14: 159.55444 | Q14: 160.82885 | R14: 162.71474 | S14: 163.9722 | T14: 163.34119 | U14: 163.73148 | V14: 163.01615 | W14: 162.25245 | X14: 162.40821 | Y14: 163.74535 | Z14: 162.07376 | AA14: 156.53468 | AB14: 148.95122 | AC14: 131.46968 | AD14: 122.04363 | AE14: 106.05459 | AF14: 80.162206 | AG14: 18.759053 | AH14: 16.758924 | AI14: 16.275032 | AJ14: 16.454136 | AK14: 16.641563 | AL14: 16.124912 | AM14: 12.489131 | AN14: 11.190328 | AO14: 10.36387 | AP14: 7.7666067 | AQ14: 7.012875 | AR14: 7.1354896 | AS14: 7.2567397 | AT14: 7.2451645 | AU14: 6.8673983 | AV14: 6.9167413 | AW14: 6.8624091 | AX14: 6.9775423 | AY14: 0 | AZ14: 0 | BA14: 0 | BB14: 0 | BC14: 0 | BD14: 0 | BE14: 0 | BF14: 0 | BG14: 0 | BH14: 0 | BI14: 0 | BJ14: 0 | BK14: 0 | BL14: 0 | BM14: 0 | BN14: 0 | BO14: 0 | BP14: 0 | BQ14: 0 | BR14: 0 | BS14: 0 | BT14: 0 | BU14: 0 | BV14: 0 | BW14: 0 | BX14: 0 | BY14: 0 | BZ14: 0 | CA14: 0 | CB14: 0 | CC14: 0 | CD14: 0 | CE14: 0 | CF14: 0 | CG14: 0 | CH14: 0 | CI14: 0 | CJ14: 0 | CK14: 0 | CL14: 0 | CM14: 0 | CN14: 0 | CO14: 0 | CP14: 0 | CQ14: 0 | CR14: 0 | CS14: 0 | CT14: 0 | CU14: 0 | CV14: 0 | CW14: 0 | CX14: 0 | CY14: 0 | CZ14: 0 | DA14: 0 | DB14: 0 | DC14: 0 | DD14: 0 | DE14: 0 | DF14: 0 | DG14: 0 | DH14: 0 | DI14: 0 | DJ14: 0 | DK14: 0 | DL14: 0 | DM14: 0 | DN14: 0 | DO14: 0 | DP14: 0 | DQ14: 0 | DR14: 0 | DS14: 0 | DT14: 0 | DU14: 0 | DV14: 0 | DW14: 0 | DX14: 0 | DY14: 0 | DZ14: 0 | EA14: 0 | EB14: 0 | EC14: 0 | ED14: 0 | EE14: 0 | EF14: 0 | EG14: 0 | EH14: 0 | EI14: 0 | EJ14: 0 | EK14: 0 | EL14: 0
B15: IG_AC | C15: 0 | D15: 0 | E15: 0 | F15: 0 | G15: 0 | H15: 0 | I15: 0 | J15: 0 | K15: 0 | L15: 0 | M15: 0 | N15: 0 | O15: 0 | P15: 0 | Q15: 0 | R15: 0 | S15: 0 | T15: 0 | U15: 0 | V15: 0 | W15: 0 | X15: 0 | Y15: 0 | Z15: 0 | AA15: 0 | AB15: 0 | AC15: 0 | AD15: 0 | AE15: 0 | AF15: 0 | AG15: 0 | AH15: 0 | AI15: 0 | AJ15: 0 | AK15: 0 | AL15: 0 | AM15: 0 | AN15: 0 | AO15: 0 | AP15: 0 | AQ15: 0 | AR15: 0 | AS15: 0 | AT15: 0 | AU15: 0 | AV15: 0 | AW15: 0 | AX15: 0 | AY15: 0 | AZ15: 0 | BA15: 0 | BB15: 0 | BC15: 0 | BD15: 0 | BE15: 0 | BF15: 0 | BG15: 0 | BH15: 0 | BI15: 0 | BJ15: 0 | BK15: 0 | BL15: 0 | BM15: 0 | BN15: 0 | BO15: 0 | BP15: 0 | BQ15: 0 | BR15: 0 | BS15: 0 | BT15: 0 | BU15: 0 | BV15: 0 | BW15: 0 | BX15: 0 | BY15: 0 | BZ15: 0 | CA15: 0 | CB15: 0 | CC15: 0 | CD15: 0 | CE15: 0 | CF15: 0 | CG15: 0 | CH15: 0 | CI15: 0 | CJ15: 0 | CK15: 0 | CL15: 0 | CM15: 0 | CN15: 0 | CO15: 0 | CP15: 0 | CQ15: 0 | CR15: 0 | CS15: 0 | CT15: 0 | CU15: 0 | CV15: 0 | CW15: 0 | CX15: 0 | CY15: 0 | CZ15: 0 | DA15: 0 | DB15: 0 | DC15: 0 | DD15: 0 | DE15: 0 | DF15: 0 | DG15: 0 | DH15: 0 | DI15: 0 | DJ15: 0 | DK15: 0 | DL15: 0 | DM15: 0 | DN15: 0 | DO15: 0 | DP15: 0 | DQ15: 0 | DR15: 0 | DS15: 0 | DT15: 0 | DU15: 0 | DV15: 0 | DW15: 0 | DX15: 0 | DY15: 0 | DZ15: 0 | EA15: 0 | EB15: 0 | EC15: 0 | ED15: 0 | EE15: 0 | EF15: 0 | EG15: 0 | EH15: 0 | EI15: 0 | EJ15: 0 | EK15: 0 | EL15: 0
B16: HY | C16: 0 | D16: 0 | E16: 0 | F16: 0 | G16: 0 | H16: 0 | I16: 0 | J16: 0 | K16: 0 | L16: 0 | M16: 0 | N16: 0 | O16: 0 | P16: 0 | Q16: 0 | R16: 0 | S16: 0 | T16: 0 | U16: 0 | V16: 0 | W16: 0 | X16: 0 | Y16: 0 | Z16: 0 | AA16: 0 | AB16: 0 | AC16: 0 | AD16: 0 | AE16: 0 | AF16: 0 | AG16: 0 | AH16: 0 | AI16: 0 | AJ16: 0 | AK16: 0 | AL16: 0 | AM16: 0 | AN16: 0 | AO16: 0 | AP16: 0 | AQ16: 0 | AR16: 0 | AS16: 0 | AT16: 0 | AU16: 0 | AV16: 0 | AW16: 0 | AX16: 0 | AY16: 0 | AZ16: 0 | BA16: 0 | BB16: 0 | BC16: 0 | BD16: 0 | BE16: 0 | BF16: 0 | BG16: 0 | BH16: 0 | BI16: 0 | BJ16: 0 | BK16: 0 | BL16: 0 | BM16: 0 | BN16: 0 | BO16: 0 | BP16: 0 | BQ16: 0 | BR16: 0 | BS16: 0 | BT16: 0 | BU16: 0 | BV16: 0 | BW16: 0 | BX16: 0 | BY16: 0 | BZ16: 0 | CA16: 0 | CB16: 0 | CC16: 0 | CD16: 0 | CE16: 0 | CF16: 0 | CG16: 0 | CH16: 0 | CI16: 0 | CJ16: 0 | CK16: 0 | CL16: 0 | CM16: 0 | CN16: 0 | CO16: 0 | CP16: 0 | CQ16: 0 | CR16: 0 | CS16: 0 | CT16: 0 | CU16: 0 | CV16: 0 | CW16: 0 | CX16: 0 | CY16: 0 | CZ16: 0 | DA16: 0 | DB16: 0 | DC16: 0 | DD16: 0 | DE16: 0 | DF16: 0 | DG16: 0 | DH16: 0 | DI16: 0 | DJ16: 0 | DK16: 0 | DL16: 0 | DM16: 0 | DN16: 0 | DO16: 0 | DP16: 0 | DQ16: 0 | DR16: 0 | DS16: 0 | DT16: 0 | DU16: 0 | DV16: 0 | DW16: 0 | DX16: 0 | DY16: 0 | DZ16: 0 | EA16: 0 | EB16: 0 | EC16: 0 | ED16: 0 | EE16: 0 | EF16: 0 | EG16: 0 | EH16: 0 | EI16: 0 | EJ16: 0 | EK16: 0 | EL16: 0

Sheet LiabilityCF
A2: ExistingLiabilityCF
B4: ExistingCF | C4: 0 | D4: 1 | E4: 2 | F4: 3 | G4: 4 | H4: 5 | I4: 6 | J4: 7 | K4: 8 | L4: 9 | M4: 10 | N4: 11 | O4: 12 | P4: 13 | Q4: 14 | R4: 15 | S4: 16 | T4: 17 | U4: 18 | V4: 19 | W4: 20 | X4: 21 | Y4: 22 | Z4: 23 | AA4: 24 | AB4: 25 | AC4: 26 | AD4: 27 | AE4: 28 | AF4: 29 | AG4: 30 | AH4: 31 | AI4: 32 | AJ4: 33 | AK4: 34 | AL4: 35 | AM4: 36 | AN4: 37 | AO4: 38 | AP4: 39 | AQ4: 40 | AR4: 41 | AS4: 42 | AT4: 43 | AU4: 44 | AV4: 45 | AW4: 46 | AX4: 47 | AY4: 48 | AZ4: 49 | BA4: 50 | BB4: 51 | BC4: 52 | BD4: 53 | BE4: 54 | BF4: 55 | BG4: 56 | BH4: 57 | BI4: 58 | BJ4: 59 | BK4: 60 | BL4: 61 | BM4: 62 | BN4: 63 | BO4: 64 | BP4: 65 | BQ4: 66 | BR4: 67 | BS4: 68 | BT4: 69 | BU4: 70 | BV4: 71 | BW4: 72 | BX4: 73 | BY4: 74 | BZ4: 75 | CA4: 76 | CB4: 77 | CC4: 78 | CD4: 79 | CE4: 80 | CF4: 81 | CG4: 82 | CH4: 83 | CI4: 84 | CJ4: 85 | CK4: 86 | CL4: 87 | CM4: 88 | CN4: 89 | CO4: 90 | CP4: 91 | CQ4: 92 | CR4: 93 | CS4: 94 | CT4: 95 | CU4: 96 | CV4: 97 | CW4: 98 | CX4: 99 | CY4: 100 | CZ4: 101 | DA4: 102 | DB4: 103 | DC4: 104 | DD4: 105 | DE4: 106 | DF4: 107 | DG4: 108 | DH4: 109 | DI4: 110 | DJ4: 111 | DK4: 112 | DL4: 113 | DM4: 114 | DN4: 115 | DO4: 116 | DP4: 117 | DQ4: 118 | DR4: 119 | DS4: 120 | DT4: 121 | DU4: 122 | DV4: 123 | DW4: 124 | DX4: 125 | DY4: 126 | DZ4: 127 | EA4: 128 | EB4: 129 | EC4: 130 | ED4: 131 | EE4: 132 | EF4: 133 | EG4: 134 | EH4: 135 | EI4: 136 | EJ4: 137 | EK4: 138 | EL4: 139
B5: Existing CF Beg | C5: 0 | D5: 157.1362 | E5: 96.610158 | F5: 65.549304 | G5: 31.393519 | H5: 0.58748696 | I5: 0.37517083 | J5: 0.22717929 | K5: 0.11492 | L5: 0.10600013 | M5: 0.085626838 | N5: 0.081849036 | O5: 0.078909286 | P5: 0.07645046 | Q5: 0.073371234 | R5: 0.068345447 | S5: 0.064937595 | T5: 0.061628362 | U5: 0.058605539 | V5: 0.054398748 | W5: 0.031573064 | X5: 0.025783409 | Y5: 0.021530561 | Z5: 0.019875679 | AA5: 0.018509247 | AB5: 0.00048687534 | AC5: 0 | AD5: 0 | AE5: 0 | AF5: 0 | AG5: 0 | AH5: 0 | AI5: 0 | AJ5: 0 | AK5: 0 | AL5: 0 | AM5: 0 | AN5: 0 | AO5: 0 | AP5: 0 | AQ5: 0 | AR5: 0 | AS5: 0 | AT5: 0 | AU5: 0 | AV5: 0 | AW5: 0 | AX5: 0 | AY5: 0 | AZ5: 0 | BA5: 0 | BB5: 0 | BC5: 0 | BD5: 0 | BE5: 0 | BF5: 0 | BG5: 0 | BH5: 0 | BI5: 0 | BJ5: 0 | BK5: 0 | BL5: 0 | BM5: 0 | BN5: 0 | BO5: 0 | BP5: 0 | BQ5: 0 | BR5: 0 | BS5: 0 | BT5: 0 | BU5: 0 | BV5: 0 | BW5: 0 | BX5: 0 | BY5: 0 | BZ5: 0 | CA5: 0 | CB5: 0 | CC5: 0 | CD5: 0 | CE5: 0 | CF5: 0 | CG5: 0 | CH5: 0 | CI5: 0 | CJ5: 0 | CK5: 0 | CL5: 0 | CM5: 0 | CN5: 0 | CO5: 0 | CP5: 0 | CQ5: 0 | CR5: 0 | CS5: 0 | CT5: 0 | CU5: 0 | CV5: 0 | CW5: 0 | CX5: 0 | CY5: 0 | CZ5: 0 | DA5: 0 | DB5: 0 | DC5: 0 | DD5: 0 | DE5: 0 | DF5: 0 | DG5: 0 | DH5: 0 | DI5: 0 | DJ5: 0 | DK5: 0 | DL5: 0 | DM5: 0 | DN5: 0 | DO5: 0 | DP5: 0 | DQ5: 0 | DR5: 0 | DS5: 0 | DT5: 0 | DU5: 0 | DV5: 0 | DW5: 0 | DX5: 0 | DY5: 0 | DZ5: 0 | EA5: 0 | EB5: 0 | EC5: 0 | ED5: 0 | EE5: 0 | EF5: 0 | EG5: 0 | EH5: 0 | EI5: 0 | EJ5: 0 | EK5: 0 | EL5: 0
B6: Existing Gua CF End | C6: 0 | D6: -8.7361245 | E6: -11.565252 | F6: -14.914699 | G6: -20.311022 | H6: -30.725002 | I6: -42.216237 | J6: -47.010825 | K6: -40.93181 | L6: -32.763175 | M6: -23.236439 | N6: -17.253504 | O6: -15.293212 | P6: -15.236044 | Q6: -15.466339 | R6: -15.706515 | S6: -15.966228 | T6: -16.226628 | U6: -16.456645 | V6: -16.678377 | W6: -16.897626 | X6: -17.111307 | Y6: -17.31328 | Z6: -17.495871 | AA6: -17.65426 | AB6: -17.781094 | AC6: -17.868951 | AD6: -17.911777 | AE6: -17.907719 | AF6: -17.860179 | AG6: -17.758524 | AH6: -17.604741 | AI6: -17.386982 | AJ6: -17.1093 | AK6: -16.772505 | AL6: -16.37615 | AM6: -15.923006 | AN6: -15.416091 | AO6: -14.858016 | AP6: -14.255966 | AQ6: -13.616922 | AR6: -12.953578 | AS6: -12.278645 | AT6: -11.600838 | AU6: -10.926005 | AV6: -10.25955 | AW6: -9.6088798 | AX6: -8.9776762 | AY6: -8.3639123 | AZ6: -7.7714803 | BA6: -7.2002819 | BB6: -6.6496923 | BC6: -6.1207492 | BD6: -5.6168875 | BE6: -5.1358093 | BF6: -4.6786 | BG6: -4.2479834 | BH6: -3.8417462 | BI6: -3.4590193 | BJ6: -3.1015775 | BK6: -2.76963 | BL6: -2.4616254 | BM6: -2.179667 | BN6: -1.9231132 | BO6: -1.6925146 | BP6: -1.485141 | BQ6: -1.3007376 | BR6: -1.1363749 | BS6: -0.99558484 | BT6: -0.87271562 | BU6: -0.76765293 | BV6: -0.67635744 | BW6: -0.59711859 | BX6: -0.52891988 | BY6: -0.46885801 | BZ6: -0.41696724 | CA6: -0.37091257 | CB6: -0.33185498 | CC6: -0.29833632 | CD6: -0.27008304 | CE6: -0.24666932 | CF6: -0.22649569 | CG6: -0.21023691 | CH6: -0.19704696 | CI6: -0.18533927 | CJ6: -0.17479599 | CK6: -0.16408724 | CL6: -0.1544435 | CM6: -0.14374299 | CN6: -0.13350061 | CO6: -0.12327605 | CP6: -0.11349214 | CQ6: -0.10253105 | CR6: -0.092709297 | CS6: -0.081800176 | CT6: -0.071489285 | CU6: -0.061967293 | CV6: -0.051374643 | CW6: -0.040918237 | CX6: -0.03199676 | CY6: -0.024998589 | CZ6: -0.016862127 | DA6: -0.012257789 | DB6: -0.0085171985 | DC6: -0.00560311 | DD6: -0.0034482635 | DE6: -0.0019535368 | DF6: -0.00099777377 | DG6: -0.00044570818 | DH6: -0.00016718372 | DI6: -4.8880314e-05 | DJ6: -1.1231362e-05 | DK6: -2.2120722e-06 | DL6: -4.3565868e-07 | DM6: -8.5806208e-08 | DN6: -1.6900187e-08 | DO6: -3.3285933e-09 | DP6: -6.5555111e-10 | DQ6: -1.2911108e-10 | DR6: -2.5427534e-11 | DS6: -5.0082694e-12 | DT6: -9.8633613e-13 | DU6: -1.9425227e-13 | DV6: -3.8256779e-14 | DW6: -7.5343941e-15 | DX6: -1.483857e-15 | DY6: -2.9223884e-16 | DZ6: -5.7558782e-17 | EA6: -1.1336592e-17 | EB6: -2.2328784e-18 | EC6: -4.397894e-19 | ED6: -8.662145e-20 | EE6: -1.7060664e-20 | EF6: -3.3600221e-21 | EG6: -6.6153184e-22 | EH6: -1.3035433e-22 | EI6: -2.5596824e-23 | EJ6: -4.8475206e-24 | EK6: -5.4131071e-25 | EL6: 0
B7: Existing Non-Guar AD | C7: 0 | D7: -0.24255397 | E7: -0.45382535 | F7: -0.43965134 | G7: -0.4201688 | H7: -1.4083588 | I7: -1.3674452 | J7: -1.330748 | K7: -1.297083 | L7: -1.2635066 | M7: -1.229997 | N7: -1.1965014 | O7: -1.1629887 | P7: -1.12943 | Q7: -1.095802 | R7: -1.0620871 | S7: -1.0282743 | T7: -0.99436184 | U7: -0.96035568 | V7: -0.92627345 | W7: -0.89214192 | X7: -0.85799853 | Y7: -0.82389071 | Z7: -0.78987502 | AA7: -0.75601539 | AB7: -0.72238077 | AC7: -0.68904354 | AD7: -0.65607728 | AE7: -0.6235559 | AF7: -0.5915521 | AG7: -0.56558366 | AH7: -0.53666972 | AI7: -0.50568076 | AJ7: -0.4754527 | AK7: -0.44677958 | AL7: -0.41880336 | AM7: -0.39204831 | AN7: -0.36635833 | AO7: -0.34128829 | AP7: -0.3175585 | AQ7: -0.2953067 | AR7: -0.27416984 | AS7: -0.25439735 | AT7: -0.2357709 | AU7: -0.21822353 | AV7: -0.20154915 | AW7: -0.18603847 | AX7: -0.17158217 | AY7: -0.15792586 | AZ7: -0.14534439 | BA7: -0.13364938 | BB7: -0.12280715 | BC7: -0.11287728 | BD7: -0.10369433 | BE7: -0.095293066 | BF7: -0.087479426 | BG7: -0.080442268 | BH7: -0.073951601 | BI7: -0.068114338 | BJ7: -0.062756783 | BK7: -0.057821598 | BL7: -0.053421692 | BM7: -0.049381048 | BN7: -0.045783583 | BO7: -0.042530727 | BP7: -0.039586822 | BQ7: -0.036913161 | BR7: -0.034495779 | BS7: -0.032276403 | BT7: -0.030210018 | BU7: -0.028306498 | BV7: -0.026542697 | BW7: -0.02488743 | BX7: -0.023326399 | BY7: -0.021840255 | BZ7: -0.020430393 | CA7: -0.019085319 | CB7: -0.017791471 | CC7: -0.016541254 | CD7: -0.015328505 | CE7: -0.014148782 | CF7: -0.012999399 | CG7: -0.011879827 | CH7: -0.01079144 | CI7: -0.0097371232 | CJ7: -0.0087208732 | CK7: -0.0077473213 | CL7: -0.0068213052 | CM7: -0.005947641 | CN7: -0.0051309102 | CO7: -0.0043752569 | CP7: -0.0036841631 | CQ7: -0.0030602305 | CR7: -0.0025049634 | CS7: -0.0020185277 | CT7: -0.0015996047 | CU7: -0.0012452824 | CV7: -0.00095116584 | CW7: -0.00071161987 | CX7: -0.00052021348 | CY7: -0.00037024088 | CZ7: -0.00025520467 | DA7: -0.00016917233 | DB7: -0.00010685576 | DC7: -6.3561068e-05 | DD7: -3.5096089e-05 | DE7: -1.7658522e-05 | DF7: -7.8969133e-06 | DG7: -3.0288392e-06 | DH7: -9.4573513e-07 | DI7: -2.1929322e-07 | DJ7: -4.2983158e-08 | DK7: -8.4250174e-09 | DL7: -1.6513635e-09 | DM7: -3.2367855e-10 | DN7: -6.3443122e-11 | DO7: -1.2435251e-11 | DP7: -2.4373839e-12 | DQ7: -4.7774121e-13 | DR7: -9.3639881e-14 | DS7: -1.8353901e-14 | DT7: -3.5974543e-15 | DU7: -7.0511762e-16 | DV7: -1.3820611e-16 | DW7: -2.7088956e-17 | DX7: -5.3095375e-18 | DY7: -1.0406879e-18 | DZ7: -2.0397816e-19 | EA7: -3.9980317e-20 | EB7: -7.8362463e-21 | EC7: -1.5359203e-21 | ED7: -3.0104252e-22 | EE7: -5.90043e-23 | EF7: -1.1564515e-23 | EG7: -2.2660945e-24 | EH7: -4.4370492e-25 | EI7: -8.6387324e-26 | EJ7: -1.6772435e-26 | EK7: -1.6336318e-27 | EL7: 0
B8: Existing Non-Guar TD | C8: 0 | D8: -0.080589248 | E8: -0.2614782 | F8: -0.62631891 | G8: -1.8656562 | H8: -5.5287108 | I8: -10.494271 | J8: -13.551517 | K8: -13.726686 | L8: -12.661872 | M8: -10.249601 | N8: -8.6241744 | O8: -8.4360078 | P8: -9.1621716 | Q8: -10.229492 | R8: -11.429927 | S8: -12.775823 | T8: -14.262621 | U8: -15.849413 | V8: -17.541348 | W8: -19.374481 | X8: -21.339712 | Y8: -23.465404 | Z8: -25.652296 | AA8: -27.867807 | AB8: -30.144117 | AC8: -32.482515 | AD8: -34.886519 | AE8: -37.166726 | AF8: -39.328916 | AG8: -41.462093 | AH8: -43.565955 | AI8: -45.770808 | AJ8: -47.833129 | AK8: -49.708525 | AL8: -51.461467 | AM8: -53.071583 | AN8: -54.503796 | AO8: -55.815462 | AP8: -56.987506 | AQ8: -57.909608 | AR8: -58.557092 | AS8: -58.886317 | AT8: -58.993713 | AU8: -58.863347 | AV8: -58.502419 | AW8: -57.961855 | AX8: -57.21469 | AY8: -56.338597 | AZ8: -55.387686 | BA8: -54.323103 | BB8: -53.164964 | BC8: -51.809284 | BD8: -50.336891 | BE8: -48.752099 | BF8: -47.016295 | BG8: -45.212833 | BH8: -43.315103 | BI8: -41.366758 | BJ8: -39.420483 | BK8: -37.46979 | BL8: -35.487003 | BM8: -33.468303 | BN8: -31.47181 | BO8: -29.545368 | BP8: -27.668465 | BQ8: -25.916198 | BR8: -24.268238 | BS8: -22.790111 | BT8: -21.423183 | BU8: -20.232668 | BV8: -19.161188 | BW8: -18.195807 | BX8: -17.362671 | BY8: -16.62179 | BZ8: -15.995761 | CA8: -15.474169 | CB8: -15.031413 | CC8: -14.686419 | CD8: -14.461512 | CE8: -14.377892 | CF8: -14.390007 | CG8: -14.511525 | CH8: -14.696629 | CI8: -14.929046 | CJ8: -15.16793 | CK8: -15.406994 | CL8: -15.599884 | CM8: -15.674043 | CN8: -15.71119 | CO8: -15.591887 | CP8: -15.439889 | CQ8: -15.026742 | CR8: -14.565689 | CS8: -13.906548 | CT8: -13.130703 | CU8: -12.275882 | CV8: -11.172218 | CW8: -9.8683555 | CX8: -8.5263797 | CY8: -7.2832527 | CZ8: -5.7356629 | DA8: -4.5215363 | DB8: -3.4089516 | DC8: -2.4345234 | DD8: -1.6269963 | DE8: -0.9999017 | DF8: -0.55350772 | DG8: -0.26788349 | DH8: -0.10895041 | DI8: -0.034185576 | DJ8: -0.008441381 | DK8: -0.0017724292 | DL8: -0.00037209901 | DM8: -7.8123999e-05 | DN8: -1.6408963e-05 | DO8: -3.4466254e-06 | DP8: -7.2414843e-07 | DQ8: -1.5243836e-07 | DR8: -3.2092926e-08 | DS8: -6.7594045e-09 | DT8: -1.424974e-09 | DU8: -2.9904963e-10 | DV8: -6.276048e-11 | DW8: -1.3171113e-11 | DX8: -2.7641978e-12 | DY8: -5.8013118e-13 | DZ8: -1.2175759e-13 | EA8: -2.555595e-14 | EB8: -5.3639341e-15 | EC8: -1.1259156e-15 | ED8: -2.3633775e-16 | EE8: -4.9606824e-17 | EF8: -1.0413099e-17 | EG8: -2.1854197e-18 | EH8: -4.5917703e-19 | EI8: -9.6219558e-20 | EJ8: -2.0762141e-20 | EK8: -3.1574234e-21 | EL8: 0
B9: Existing PC | C9: 0 | D9: -9.2345383 | E9: -5.1722488 | F9: -3.3489432 | G9: -1.6162146 | H9: -0.0023959212 | I9: 0 | J9: 0 | K9: 0 | L9: 0 | M9: 0 | N9: 0 | O9: 0 | P9: 0 | Q9: 0 | R9: 0 | S9: 0 | T9: 0 | U9: 0 | V9: 0 | W9: 0 | X9: 0 | Y9: 0 | Z9: 0 | AA9: 0 | AB9: 0 | AC9: 0 | AD9: 0 | AE9: 0 | AF9: 0 | AG9: 0 | AH9: 0 | AI9: 0 | AJ9: 0 | AK9: 0 | AL9: 0 | AM9: 0 | AN9: 0 | AO9: 0 | AP9: 0 | AQ9: 0 | AR9: 0 | AS9: 0 | AT9: 0 | AU9: 0 | AV9: 0 | AW9: 0 | AX9: 0 | AY9: 0 | AZ9: 0 | BA9: 0 | BB9: 0 | BC9: 0 | BD9: 0 | BE9: 0 | BF9: 0 | BG9: 0 | BH9: 0 | BI9: 0 | BJ9: 0 | BK9: 0 | BL9: 0 | BM9: 0 | BN9: 0 | BO9: 0 | BP9: 0 | BQ9: 0 | BR9: 0 | BS9: 0 | BT9: 0 | BU9: 0 | BV9: 0 | BW9: 0 | BX9: 0 | BY9: 0 | BZ9: 0 | CA9: 0 | CB9: 0 | CC9: 0 | CD9: 0 | CE9: 0 | CF9: 0 | CG9: 0 | CH9: 0 | CI9: 0 | CJ9: 0 | CK9: 0 | CL9: 0 | CM9: 0 | CN9: 0 | CO9: 0 | CP9: 0 | CQ9: 0 | CR9: 0 | CS9: 0 | CT9: 0 | CU9: 0 | CV9: 0 | CW9: 0 | CX9: 0 | CY9: 0 | CZ9: 0 | DA9: 0 | DB9: 0 | DC9: 0 | DD9: 0 | DE9: 0 | DF9: 0 | DG9: 0 | DH9: 0 | DI9: 0 | DJ9: 0 | DK9: 0 | DL9: 0 | DM9: 0 | DN9: 0 | DO9: 0 | DP9: 0 | DQ9: 0 | DR9: 0 | DS9: 0 | DT9: 0 | DU9: 0 | DV9: 0 | DW9: 0 | DX9: 0 | DY9: 0 | DZ9: 0 | EA9: 0 | EB9: 0 | EC9: 0 | ED9: 0 | EE9: 0 | EF9: 0 | EG9: 0 | EH9: 0 | EI9: 0 | EJ9: 0 | EK9: 0 | EL9: 0
B10: Existing AMC | C10: 0 | D10: -0.96921908 | E10: -1.2922209 | F10: -1.5408614 | G10: -1.7148611 | H10: -1.8019294 | I10: -1.819106 | J10: -1.8043699 | K10: -1.7928081 | L10: -1.8055504 | M10: -1.872662 | N10: -2.0277039 | O10: -2.161627 | P10: -2.2597225 | Q10: -2.3619316 | R10: -2.6011461 | S10: -4.9209952 | T10: -6.445369 | U10: -6.6522128 | V10: -6.8607566 | W10: -7.097014 | X10: -7.3347951 | Y10: -7.5452591 | Z10: -7.7542294 | AA10: -7.9777603 | AB10: -8.7518917 | AC10: -9.2614305 | AD10: -9.501425 | AE10: -9.7416846 | AF10: -9.9841743 | AG10: -10.407424 | AH10: -10.744186 | AI10: -11.005778 | AJ10: -11.273226 | AK10: -11.54969 | AL10: -11.838416 | AM10: -12.143245 | AN10: -12.463622 | AO10: -12.801698 | AP10: -13.166549 | AQ10: -13.560753 | AR10: -13.986609 | AS10: -14.449584 | AT10: -14.950466 | AU10: -15.491819 | AV10: -16.077757 | AW10: -16.714013 | AX10: -17.402367 | AY10: -18.144572 | AZ10: -18.946393 | BA10: -19.810033 | BB10: -20.74257 | BC10: -21.747115 | BD10: -22.82833 | BE10: -23.988717 | BF10: -25.227342 | BG10: -26.542951 | BH10: -27.956863 | BI10: -29.458058 | BJ10: -31.043553 | BK10: -32.727559 | BL10: -34.502497 | BM10: -36.374621 | BN10: -38.321569 | BO10: -40.323714 | BP10: -42.297 | BQ10: -44.278157 | BR10: -46.305355 | BS10: -48.493752 | BT10: -50.781462 | BU10: -52.993171 | BV10: -54.999952 | BW10: -56.833842 | BX10: -58.410728 | BY10: -60.012122 | BZ10: -61.452332 | CA10: -62.534301 | CB10: -63.431161 | CC10: -63.64585 | CD10: -63.805066 | CE10: -63.865872 | CF10: -64.608583 | CG10: -65.375684 | CH10: -64.300376 | CI10: -63.670136 | CJ10: -63.311807 | CK10: -62.542305 | CL10: -62.176093 | CM10: -61.573119 | CN10: -60.798574 | CO10: -59.517248 | CP10: -58.147557 | CQ10: -56.4414 | CR10: -55.161101 | CS10: -53.327921 | CT10: -51.717589 | CU10: -48.431187 | CV10: -45.440628 | CW10: -42.10174 | CX10: -39.9352 | CY10: -37.960008 | CZ10: -35.11574 | DA10: -31.924253 | DB10: -29.525295 | DC10: -27.880428 | DD10: -26.573201 | DE10: -25.749444 | DF10: -24.78722 | DG10: -24.23929 | DH10: -22.527305 | DI10: -20.248317 | DJ10: -18.150952 | DK10: -16.923714 | DL10: -14.110182 | DM10: -12.024199 | DN10: -11.539243 | DO10: -11.381346 | DP10: -11.424323 | DQ10: -11.344784 | DR10: -11.318492 | DS10: -11.502441 | DT10: -11.325238 | DU10: -10.963731 | DV10: -10.592092 | DW10: -10.333332 | DX10: -10.376161 | DY10: -9.9782633 | DZ10: -9.8053199 | EA10: -9.5741778 | EB10: -8.1661888 | EC10: -6.8625064 | ED10: -6.4796278 | EE10: -5.7728104 | EF10: -4.6899943 | EG10: -3.7699147 | EH10: -3.1801327 | EI10: -2.1064249 | EJ10: -0.69908556 | EK10: -0.13927276 | EL10: 0
A15: NBCF
B17: NBCF | C17: 0 | D17: 1 | E17: 2 | F17: 3 | G17: 4 | H17: 5 | I17: 6 | J17: 7 | K17: 8 | L17: 9 | M17: 10 | N17: 11 | O17: 12 | P17: 13 | Q17: 14 | R17: 15 | S17: 16 | T17: 17 | U17: 18 | V17: 19 | W17: 20 | X17: 21 | Y17: 22 | Z17: 23 | AA17: 24 | AB17: 25 | AC17: 26 | AD17: 27 | AE17: 28 | AF17: 29 | AG17: 30 | AH17: 31 | AI17: 32 | AJ17: 33 | AK17: 34 | AL17: 35 | AM17: 36 | AN17: 37 | AO17: 38 | AP17: 39 | AQ17: 40 | AR17: 41 | AS17: 42 | AT17: 43 | AU17: 44 | AV17: 45 | AW17: 46 | AX17: 47 | AY17: 48 | AZ17: 49 | BA17: 50 | BB17: 51 | BC17: 52 | BD17: 53 | BE17: 54 | BF17: 55 | BG17: 56 | BH17: 57 | BI17: 58 | BJ17: 59 | BK17: 60 | BL17: 61 | BM17: 62 | BN17: 63 | BO17: 64 | BP17: 65 | BQ17: 66 | BR17: 67 | BS17: 68 | BT17: 69 | BU17: 70 | BV17: 71 | BW17: 72 | BX17: 73 | BY17: 74 | BZ17: 75 | CA17: 76 | CB17: 77 | CC17: 78 | CD17: 79 | CE17: 80 | CF17: 81 | CG17: 82 | CH17: 83 | CI17: 84 | CJ17: 85 | CK17: 86 | CL17: 87 | CM17: 88 | CN17: 89 | CO17: 90 | CP17: 91 | CQ17: 92 | CR17: 93 | CS17: 94 | CT17: 95 | CU17: 96 | CV17: 97 | CW17: 98 | CX17: 99 | CY17: 100 | CZ17: 101 | DA17: 102 | DB17: 103 | DC17: 104 | DD17: 105 | DE17: 106 | DF17: 107 | DG17: 108 | DH17: 109 | DI17: 110 | DJ17: 111 | DK17: 112 | DL17: 113 | DM17: 114 | DN17: 115 | DO17: 116 | DP17: 117 | DQ17: 118 | DR17: 119 | DS17: 120 | DT17: 121 | DU17: 122 | DV17: 123 | DW17: 124 | DX17: 125 | DY17: 126 | DZ17: 127 | EA17: 128 | EB17: 129 | EC17: 130 | ED17: 131 | EE17: 132 | EF17: 133 | EG17: 134 | EH17: 135 | EI17: 136 | EJ17: 137 | EK17: 138 | EL17: 139
B18: NB Inflow | C18: 0 | D18: 79.945 | E18: 158.28781 | F18: 228.17772 | G18: 300.39462 | H18: 241.33982 | I18: 169.73675 | J18: 119.55037 | K18: 65.074757 | L18: 7.4597354 | M18: 7.3222657 | N18: 6.2320687 | O18: 4.6809454 | P18: 2.5504787 | Q18: 0 | R18: 0 | S18: 0 | T18: 0 | U18: 0 | V18: 0 | W18: 0 | X18: 0 | Y18: 0 | Z18: 0 | AA18: 0 | AB18: 0 | AC18: 0 | AD18: 0 | AE18: 0 | AF18: 0 | AG18: 0 | AH18: 0 | AI18: 0 | AJ18: 0 | AK18: 0 | AL18: 0 | AM18: 0 | AN18: 0 | AO18: 0 | AP18: 0 | AQ18: 0 | AR18: 0 | AS18: 0 | AT18: 0 | AU18: 0 | AV18: 0 | AW18: 0 | AX18: 0 | AY18: 0 | AZ18: 0 | BA18: 0 | BB18: 0 | BC18: 0 | BD18: 0 | BE18: 0 | BF18: 0 | BG18: 0 | BH18: 0 | BI18: 0 | BJ18: 0 | BK18: 0 | BL18: 0 | BM18: 0 | BN18: 0 | BO18: 0 | BP18: 0 | BQ18: 0 | BR18: 0 | BS18: 0 | BT18: 0 | BU18: 0 | BV18: 0 | BW18: 0 | BX18: 0 | BY18: 0 | BZ18: 0 | CA18: 0 | CB18: 0 | CC18: 0 | CD18: 0 | CE18: 0 | CF18: 0 | CG18: 0 | CH18: 0 | CI18: 0 | CJ18: 0 | CK18: 0 | CL18: 0 | CM18: 0 | CN18: 0 | CO18: 0 | CP18: 0 | CQ18: 0 | CR18: 0 | CS18: 0 | CT18: 0 | CU18: 0 | CV18: 0 | CW18: 0 | CX18: 0 | CY18: 0 | CZ18: 0 | DA18: 0 | DB18: 0 | DC18: 0 | DD18: 0 | DE18: 0 | DF18: 0 | DG18: 0 | DH18: 0 | DI18: 0 | DJ18: 0 | DK18: 0 | DL18: 0 | DM18: 0 | DN18: 0 | DO18: 0 | DP18: 0 | DQ18: 0 | DR18: 0 | DS18: 0 | DT18: 0 | DU18: 0 | DV18: 0 | DW18: 0 | DX18: 0 | DY18: 0 | DZ18: 0 | EA18: 0 | EB18: 0 | EC18: 0 | ED18: 0 | EE18: 0 | EF18: 0 | EG18: 0 | EH18: 0 | EI18: 0 | EJ18: 0 | EK18: 0 | EL18: 0
B19: NB Guar Outflow | C19: 0 | D19: -45.952014 | E19: -58.499508 | F19: -69.238308 | G19: -79.844118 | H19: -15.304253 | I19: -17.964666 | J19: -28.174728 | K19: -44.254969 | L19: -57.682093 | M19: -68.405422 | N19: -64.874224 | O19: -49.693676 | P19: -36.830209 | Q19: -26.907442 | R19: -23.057608 | S19: -23.083631 | T19: -23.5093 | U19: -23.89465 | V19: -24.234571 | W19: -24.539166 | X19: -24.823371 | Y19: -25.095399 | Z19: -25.354171 | AA19: -25.597496 | AB19: -25.815558 | AC19: -25.992479 | AD19: -26.129853 | AE19: -26.222183 | AF19: -26.272112 | AG19: -26.285573 | AH19: -26.24549 | AI19: -26.152738 | AJ19: -26.005798 | AK19: -25.810586 | AL19: -25.561934 | AM19: -25.257422 | AN19: -24.896565 | AO19: -24.466637 | AP19: -23.982203 | AQ19: -23.449929 | AR19: -22.877328 | AS19: -22.272028 | AT19: -21.629164 | AU19: -20.950492 | AV19: -20.251503 | AW19: -19.537625 | AX19: -18.808777 | AY19: -18.064909 | AZ19: -17.311628 | BA19: -16.560661 | BB19: -15.820406 | BC19: -15.082444 | BD19: -14.353946 | BE19: -13.641775 | BF19: -12.942486 | BG19: -12.25554 | BH19: -11.578826 | BI19: -10.908612 | BJ19: -10.256407 | BK19: -9.6393258 | BL19: -9.0431108 | BM19: -8.4748989 | BN19: -7.9334177 | BO19: -7.4153422 | BP19: -6.9275112 | BQ19: -6.4665282 | BR19: -5.9899026 | BS19: -5.5052848 | BT19: -5.002046 | BU19: -4.5198211 | BV19: -4.2107928 | BW19: -3.9835592 | BX19: -3.7974472 | BY19: -3.6460182 | BZ19: -3.5242241 | CA19: -3.4348356 | CB19: -3.3632229 | CC19: -3.3015977 | CD19: -3.2397624 | CE19: -3.1715955 | CF19: -3.0956744 | CG19: -2.9929288 | CH19: -2.8749848 | CI19: -2.7510323 | CJ19: -2.6164853 | CK19: -2.4890755 | CL19: -2.3466654 | CM19: -2.1879792 | CN19: -2.0057205 | CO19: -1.8013141 | CP19: -1.5973928 | CQ19: -1.395964 | CR19: -1.2153734 | CS19: -1.0398501 | CT19: -0.86548628 | CU19: -0.70380033 | CV19: -0.55782114 | CW19: -0.42883784 | CX19: -0.32265354 | CY19: -0.23499496 | CZ19: -0.1687928 | DA19: 0 | DB19: 0 | DC19: 0 | DD19: 0 | DE19: 0 | DF19: 0 | DG19: 0 | DH19: 0 | DI19: 0 | DJ19: 0 | DK19: 0 | DL19: 0 | DM19: 0 | DN19: 0 | DO19: 0 | DP19: 0 | DQ19: 0 | DR19: 0 | DS19: 0 | DT19: 0 | DU19: 0 | DV19: 0 | DW19: 0 | DX19: 0 | DY19: 0 | DZ19: 0 | EA19: 0 | EB19: 0 | EC19: 0 | ED19: 0 | EE19: 0 | EF19: 0 | EG19: 0 | EH19: 0 | EI19: 0 | EJ19: 0 | EK19: 0 | EL19: 0
B20: NB Non-Guar Outflow | C20: 0 | D20: 0 | E20: -0.36874133 | F20: -0.82244193 | G20: -1.5182864 | H20: -2.2986552 | I20: -3.9031472 | J20: -7.6034809 | K20: -14.81074 | L20: -22.136325 | M20: -27.62527 | N20: -29.556802 | O20: -25.842919 | P20: -22.90488 | Q20: -19.53984 | R20: -18.494418 | S20: -19.218595 | T20: -20.326902 | U20: -21.613119 | V20: -23.095923 | W20: -24.750166 | X20: -26.712924 | Y20: -28.914143 | Z20: -31.325443 | AA20: -33.899928 | AB20: -36.570382 | AC20: -39.419614 | AD20: -42.381253 | AE20: -45.48819 | AF20: -48.789625 | AG20: -52.178311 | AH20: -55.66256 | AI20: -59.193561 | AJ20: -62.529064 | AK20: -65.871479 | AL20: -69.141032 | AM20: -72.30586 | AN20: -75.510503 | AO20: -78.763924 | AP20: -82.046195 | AQ20: -85.264099 | AR20: -88.501689 | AS20: -91.628378 | AT20: -94.571638 | AU20: -97.300078 | AV20: -99.667809 | AW20: -101.77332 | AX20: -103.57719 | AY20: -105.05897 | AZ20: -106.23012 | BA20: -107.03967 | BB20: -107.47921 | BC20: -107.62087 | BD20: -107.54922 | BE20: -107.36117 | BF20: -107.04187 | BG20: -106.46484 | BH20: -105.62619 | BI20: -104.45488 | BJ20: -103.00768 | BK20: -101.36047 | BL20: -99.51037 | BM20: -97.469441 | BN20: -95.257858 | BO20: -92.895043 | BP20: -90.403057 | BQ20: -87.795689 | BR20: -85.131785 | BS20: -82.469408 | BT20: -79.830018 | BU20: -77.306871 | BV20: -75.010704 | BW20: -73.022226 | BX20: -71.467011 | BY20: -70.410038 | BZ20: -69.880335 | CA20: -70.002643 | CB20: -70.674032 | CC20: -71.795766 | CD20: -73.323643 | CE20: -74.975513 | CF20: -76.796532 | CG20: -78.559161 | CH20: -80.203158 | CI20: -81.855889 | CJ20: -83.269126 | CK20: -84.715069 | CL20: -85.869549 | CM20: -86.594737 | CN20: -86.812374 | CO20: -86.073741 | CP20: -84.439361 | CQ20: -81.604753 | CR20: -77.432993 | CS20: -72.342613 | CT20: -65.980981 | CU20: -59.014128 | CV20: -51.661435 | CW20: -44.061236 | CX20: -36.843906 | CY20: -29.993597 | CZ20: -24.416952 | DA20: 0 | DB20: 0 | DC20: 0 | DD20: 0 | DE20: 0 | DF20: 0 | DG20: 0 | DH20: 0 | DI20: 0 | DJ20: 0 | DK20: 0 | DL20: 0 | DM20: 0 | DN20: 0 | DO20: 0 | DP20: 0 | DQ20: 0 | DR20: 0 | DS20: 0 | DT20: 0 | DU20: 0 | DV20: 0 | DW20: 0 | DX20: 0 | DY20: 0 | DZ20: 0 | EA20: 0 | EB20: 0 | EC20: 0 | ED20: 0 | EE20: 0 | EF20: 0 | EG20: 0 | EH20: 0 | EI20: 0 | EJ20: 0 | EK20: 0 | EL20: 0
B21: NB PC | C21: 0 | D21: -4.28493 | E21: -7.3197967 | F21: -10.371259 | G21: -13.556189 | H21: -9.2392415 | I21: -7.0743541 | J21: -5.0057175 | K21: -2.6230977 | L21: -4.0364752e-05 | M21: 0 | N21: 0 | O21: 0 | P21: 0 | Q21: 0 | R21: 0 | S21: 0 | T21: 0 | U21: 0 | V21: 0 | W21: 0 | X21: 0 | Y21: 0 | Z21: 0 | AA21: 0 | AB21: 0 | AC21: 0 | AD21: 0 | AE21: 0 | AF21: 0 | AG21: 0 | AH21: 0 | AI21: 0 | AJ21: 0 | AK21: 0 | AL21: 0 | AM21: 0 | AN21: 0 | AO21: 0 | AP21: 0 | AQ21: 0 | AR21: 0 | AS21: 0 | AT21: 0 | AU21: 0 | AV21: 0 | AW21: 0 | AX21: 0 | AY21: 0 | AZ21: 0 | BA21: 0 | BB21: 0 | BC21: 0 | BD21: 0 | BE21: 0 | BF21: 0 | BG21: 0 | BH21: 0 | BI21: 0 | BJ21: 0 | BK21: 0 | BL21: 0 | BM21: 0 | BN21: 0 | BO21: 0 | BP21: 0 | BQ21: 0 | BR21: 0 | BS21: 0 | BT21: 0 | BU21: 0 | BV21: 0 | BW21: 0 | BX21: 0 | BY21: 0 | BZ21: 0 | CA21: 0 | CB21: 0 | CC21: 0 | CD21: 0 | CE21: 0 | CF21: 0 | CG21: 0 | CH21: 0 | CI21: 0 | CJ21: 0 | CK21: 0 | CL21: 0 | CM21: 0 | CN21: 0 | CO21: 0 | CP21: 0 | CQ21: 0 | CR21: 0 | CS21: 0 | CT21: 0 | CU21: 0 | CV21: 0 | CW21: 0 | CX21: 0 | CY21: 0 | CZ21: 0 | DA21: 0 | DB21: 0 | DC21: 0 | DD21: 0 | DE21: 0 | DF21: 0 | DG21: 0 | DH21: 0 | DI21: 0 | DJ21: 0 | DK21: 0 | DL21: 0 | DM21: 0 | DN21: 0 | DO21: 0 | DP21: 0 | DQ21: 0 | DR21: 0 | DS21: 0 | DT21: 0 | DU21: 0 | DV21: 0 | DW21: 0 | DX21: 0 | DY21: 0 | DZ21: 0 | EA21: 0 | EB21: 0 | EC21: 0 | ED21: 0 | EE21: 0 | EF21: 0 | EG21: 0 | EH21: 0 | EI21: 0 | EJ21: 0 | EK21: 0 | EL21: 0
B22: NB AMC Charge rate | C22: 0 | D22: 0.0002282155 | E22: 0.00031081615 | F22: 0.00032681784 | G22: 0.0003471688 | H22: 0.00039711443 | I22: 0.00043653201 | J22: 0.00061935907 | K22: 0.0062181706 | L22: -0.00027635878 | M22: 0.0010882684 | N22: 0.0021739013 | O22: 0.0035455976 | P22: 0.0053366464 | Q22: 0.0037896108 | R22: 0.0026255829 | S22: 0.0025267454 | T22: 0.0025377971 | U22: 0.0025505245 | V22: 0.0025632356 | W22: 0.0025765194 | X22: 0.0027631626 | Y22: 0.0029691899 | Z22: 0.0031805507 | AA22: 0.0033897399 | AB22: 0.0033574904 | AC22: 0.0034987803 | AD22: 0.0036882778 | AE22: 0.0039234524 | AF22: 0.0041977756 | AG22: 0.0042208595 | AH22: 0.0043890661 | AI22: 0.0045901746 | AJ22: 0.0048159958 | AK22: 0.0050600747 | AL22: 0.0051274056 | AM22: 0.0052003349 | AN22: 0.0052785423 | AO22: 0.0053605369 | AP22: 0.0054442514 | AQ22: 0.0055282615 | AR22: 0.0056124595 | AS22: 0.0056945336 | AT22: 0.0057747138 | AU22: 0.0058521041 | AV22: 0.0059252057 | AW22: 0.0059956797 | AX22: 0.0060635293 | AY22: 0.0061292229 | AZ22: 0.0061911442 | BA22: 0.0062492574 | BB22: 0.0063042502 | BC22: 0.0063561633 | BD22: 0.0064042735 | BE22: 0.0064449444 | BF22: 0.0064780447 | BG22: 0.0065004817 | BH22: 0.0065109335 | BI22: 0.0065111631 | BJ22: 0.0064987404 | BK22: 0.0064721553 | BL22: 0.0064298216 | BM22: 0.0063748065 | BN22: 0.0063068442 | BO22: 0.0062280044 | BP22: 0.0061435325 | BQ22: 0.006050261 | BR22: 0.0059515806 | BS22: 0.0058481247 | BT22: 0.005743157 | BU22: 0.0056385606 | BV22: 0.0055350903 | BW22: 0.0054365255 | BX22: 0.0053399802 | BY22: 0.0052445171 | BZ22: 0.0051464358 | CA22: 0.0050387681 | CB22: 0.0049228569 | CC22: 0.0047986819 | CD22: 0.0046693297 | CE22: 0.0045414539 | CF22: 0.0044176694 | CG22: 0.0043014305 | CH22: 0.0041962422 | CI22: 0.0041061713 | CJ22: 0.0040309725 | CK22: 0.0039696633 | CL22: 0.003919553 | CM22: 0.0038804736 | CN22: 0.0038500825 | CO22: 0.0038280689 | CP22: 0.0038110644 | CQ22: 0.003794723 | CR22: 0.0037829623 | CS22: 0.0037814747 | CT22: 0.0037890683 | CU22: 0.0038096211 | CV22: 0.0038446765 | CW22: 0.0038921307 | CX22: 0.0039628095 | CY22: 0.0040481259 | CZ22: 0.004156958 | DA22: 0 | DB22: 0 | DC22: 0 | DD22: 0 | DE22: 0 | DF22: 0 | DG22: 0 | DH22: 0 | DI22: 0 | DJ22: 0 | DK22: 0 | DL22: 0 | DM22: 0 | DN22: 0 | DO22: 0 | DP22: 0 | DQ22: 0 | DR22: 0 | DS22: 0 | DT22: 0 | DU22: 0 | DV22: 0 | DW22: 0 | DX22: 0 | DY22: 0 | DZ22: 0 | EA22: 0 | EB22: 0 | EC22: 0 | ED22: 0 | EE22: 0 | EF22: 0 | EG22: 0 | EH22: 0 | EI22: 0 | EJ22: 0 | EK22: 0 | EL22: 0
